Workbook

Sheet Dashboard MD
A1: HITECH CONSTRUCTION COMPANY LIMITED
A2: ESG & ESAP · SERVICE PROVIDER PAYMENTS DASHBOARD
A4: TOTAL COMMITTED | C4: TOTAL PAID | E4: PIPELINE | G4: UNSCHEDULED | I4: PAYMENT RATE
A5: =SUM('MD Register'!F5:F102) -> 7.5247117e+08 | C5: =SUM('MD Register'!V5:V102) -> 5.0819623e+08 | E5: =SUM('MD Register'!AC5:AC102) -> 31453515 | G5: =A5-C5-E5 -> 2.1282142e+08 | I5: =IF(A5=0,0,C5/A5) -> 0.6753697
A8: Pipeline = upcoming scheduled amounts · Unscheduled = committed - paid - pipeline · Date = paid, No date = pipeline
A10: PAYMENT SUMMARY BY SERVICE PROVIDER
A11: # | B11: Service Provider | C11: Category | D11: Project | E11: Contract (₦) | F11: Paid (₦) | G11: Pipeline (₦) | H11: Unscheduled (₦) | I11: % Paid
A12: =IF(Lists!D2="","",1) -> 1 | B12: =IF(Lists!D2="","",Lists!D2) -> NCF | C12: =IF(B12="","",IFERROR(INDEX('MD Register'!C$5:C$104,MATCH(B12,'MD Register'!B$5:B$104,0)),"")) -> ESAP-BMP | D12: =IF(B12="","",IFERROR(INDEX('MD Register'!D$5:D$104,MATCH(B12,'MD Register'!B$5:B$104,0)),"")) -> LCCH SEC 1&2 | E12: =IF(B12="","",SUMIF('MD Register'!$B$5:$B$104,TRIM(B12),'MD Register'!$F$5:$F$104)) -> 82934896 | F12: =IF(B12="","",SUMIF('MD Register'!$B$5:$B$104,TRIM(B12),'MD Register'!$V$5:$V$104)) -> 62264320 | G12: =IF(B12="","",SUMIF('MD Register'!$B$5:$B$104,TRIM(B12),'MD Register'!$AC$5:$AC$104)) -> 0 | H12: =IF(B12="","",E12-F12-G12) -> 20670576 | I12: =IF(OR(B12="",E12=0),"-",F12/E12) -> 0.75076142
A13: =IF(Lists!D3="","",2) -> 2 | B13: =IF(Lists!D3="","",Lists!D3) -> DynaSmart | C13: =IF(B13="","",IFERROR(INDEX('MD Register'!C$5:C$104,MATCH(B13,'MD Register'!B$5:B$104,0)),"")) -> ESAP-SRAP | D13: =IF(B13="","",IFERROR(INDEX('MD Register'!D$5:D$104,MATCH(B13,'MD Register'!B$5:B$104,0)),"")) -> LCCH SEC 1 | E13: =IF(B13="","",SUMIF('MD Register'!$B$5:$B$104,TRIM(B13),'MD Register'!$F$5:$F$104)) -> 4.5419667e+08 | F13: =IF(B13="","",SUMIF('MD Register'!$B$5:$B$104,TRIM(B13),'MD Register'!$V$5:$V$104)) -> 2.950982e+08 | G13: =IF(B13="","",SUMIF('MD Register'!$B$5:$B$104,TRIM(B13),'MD Register'!$AC$5:$AC$104)) -> 0 | H13: =IF(B13="","",E13-F13-G13) -> 1.5909847e+08 | I13: =IF(OR(B13="",E13=0),"-",F13/E13) -> 0.64971458
A14: =IF(Lists!D4="","",3) -> 3 | B14: =IF(Lists!D4="","",Lists!D4) -> CEO Advisory | C14: =IF(B14="","",IFERROR(INDEX('MD Register'!C$5:C$104,MATCH(B14,'MD Register'!B$5:B$104,0)),"")) -> HRRA | D14: =IF(B14="","",IFERROR(INDEX('MD Register'!D$5:D$104,MATCH(B14,'MD Register'!B$5:B$104,0)),"")) -> LCCH SEC 1 | E14: =IF(B14="","",SUMIF('MD Register'!$B$5:$B$104,TRIM(B14),'MD Register'!$F$5:$F$104)) -> 10050000 | F14: =IF(B14="","",SUMIF('MD Register'!$B$5:$B$104,TRIM(B14),'MD Register'!$V$5:$V$104)) -> 6030000 | G14: =IF(B14="","",SUMIF('MD Register'!$B$5:$B$104,TRIM(B14),'MD Register'!$AC$5:$AC$104)) -> 0 | H14: =IF(B14="","",E14-F14-G14) -> 4020000 | I14: =IF(OR(B14="",E14=0),"-",F14/E14) -> 0.6
A15: =IF(Lists!D5="","",4) -> 4 | B15: =IF(Lists!D5="","",Lists!D5) -> Eddie Perez Limited | C15: =IF(B15="","",IFERROR(INDEX('MD Register'!C$5:C$104,MATCH(B15,'MD Register'!B$5:B$104,0)),"")) -> OD SURVEY | D15: =IF(B15="","",IFERROR(INDEX('MD Register'!D$5:D$104,MATCH(B15,'MD Register'!B$5:B$104,0)),"")) -> LCCH SEC 1 | E15: =IF(B15="","",SUMIF('MD Register'!$B$5:$B$104,TRIM(B15),'MD Register'!$F$5:$F$104)) -> 130664100 | F15: =IF(B15="","",SUMIF('MD Register'!$B$5:$B$104,TRIM(B15),'MD Register'!$V$5:$V$104)) -> 109481532 | G15: =IF(B15="","",SUMIF('MD Register'!$B$5:$B$104,TRIM(B15),'MD Register'!$AC$5:$AC$104)) -> 0 | H15: =IF(B15="","",E15-F15-G15) -> 21182568 | I15: =IF(OR(B15="",E15=0),"-",F15/E15) -> 0.83788533
A16: =IF(Lists!D6="","",5) -> 5 | B16: =IF(Lists!D6="","",Lists!D6) -> David Omaghomi | C16: =IF(B16="","",IFERROR(INDEX('MD Register'!C$5:C$104,MATCH(B16,'MD Register'!B$5:B$104,0)),"")) -> CRM | D16: =IF(B16="","",IFERROR(INDEX('MD Register'!D$5:D$104,MATCH(B16,'MD Register'!B$5:B$104,0)),"")) -> LCCH SEC 1&2 | E16: =IF(B16="","",SUMIF('MD Register'!$B$5:$B$104,TRIM(B16),'MD Register'!$F$5:$F$104)) -> 29964000 | F16: =IF(B16="","",SUMIF('MD Register'!$B$5:$B$104,TRIM(B16),'MD Register'!$V$5:$V$104)) -> 19964000 | G16: =IF(B16="","",SUMIF('MD Register'!$B$5:$B$104,TRIM(B16),'MD Register'!$AC$5:$AC$104)) -> 10000000 | H16: =IF(B16="","",E16-F16-G16) -> 0 | I16: =IF(OR(B16="",E16=0),"-",F16/E16) -> 0.66626619
A17: =IF(Lists!D7="","",6) -> 6 | B17: =IF(Lists!D7="","",Lists!D7) -> Ndoni Logistic | C17: =IF(B17="","",IFERROR(INDEX('MD Register'!C$5:C$104,MATCH(B17,'MD Register'!B$5:B$104,0)),"")) -> CRM | D17: =IF(B17="","",IFERROR(INDEX('MD Register'!D$5:D$104,MATCH(B17,'MD Register'!B$5:B$104,0)),"")) -> LCCH SEC 1&2 | E17: =IF(B17="","",SUMIF('MD Register'!$B$5:$B$104,TRIM(B17),'MD Register'!$F$5:$F$104)) -> 3100000 | F17: =IF(B17="","",SUMIF('MD Register'!$B$5:$B$104,TRIM(B17),'MD Register'!$V$5:$V$104)) -> 3100000 | G17: =IF(B17="","",SUMIF('MD Register'!$B$5:$B$104,TRIM(B17),'MD Register'!$AC$5:$AC$104)) -> 0 | H17: =IF(B17="","",E17-F17-G17) -> 0 | I17: =IF(OR(B17="",E17=0),"-",F17/E17) -> 1
A18: =IF(Lists!D8="","",7) -> 7 | B18: =IF(Lists!D8="","",Lists!D8) -> Hitech-CRM | C18: =IF(B18="","",IFERROR(INDEX('MD Register'!C$5:C$104,MATCH(B18,'MD Register'!B$5:B$104,0)),"")) -> ESAP SEC 1 | D18: =IF(B18="","",IFERROR(INDEX('MD Register'!D$5:D$104,MATCH(B18,'MD Register'!B$5:B$104,0)),"")) -> LCCH SEC 1 | E18: =IF(B18="","",SUMIF('MD Register'!$B$5:$B$104,TRIM(B18),'MD Register'!$F$5:$F$104)) -> 3964400 | F18: =IF(B18="","",SUMIF('MD Register'!$B$5:$B$104,TRIM(B18),'MD Register'!$V$5:$V$104)) -> 3964400 | G18: =IF(B18="","",SUMIF('MD Register'!$B$5:$B$104,TRIM(B18),'MD Register'!$AC$5:$AC$104)) -> 0 | H18: =IF(B18="","",E18-F18-G18) -> 0 | I18: =IF(OR(B18="",E18=0),"-",F18/E18) -> 1
A19: =IF(Lists!D9="","",8) -> 8 | B19: =IF(Lists!D9="","",Lists!D9) -> Beachtv Media Limited | C19: =IF(B19="","",IFERROR(INDEX('MD Register'!C$5:C$104,MATCH(B19,'MD Register'!B$5:B$104,0)),"")) -> CSR | D19: =IF(B19="","",IFERROR(INDEX('MD Register'!D$5:D$104,MATCH(B19,'MD Register'!B$5:B$104,0)),"")) -> LCCH SEC 1 | E19: =IF(B19="","",SUMIF('MD Register'!$B$5:$B$104,TRIM(B19),'MD Register'!$F$5:$F$104)) -> 370000 | F19: =IF(B19="","",SUMIF('MD Register'!$B$5:$B$104,TRIM(B19),'MD Register'!$V$5:$V$104)) -> 120000 | G19: =IF(B19="","",SUMIF('MD Register'!$B$5:$B$104,TRIM(B19),'MD Register'!$AC$5:$AC$104)) -> 250000 | H19: =IF(B19="","",E19-F19-G19) -> 0 | I19: =IF(OR(B19="",E19=0),"-",F19/E19) -> 0.32432432
A20: =IF(Lists!D10="","",9) -> 9 | B20: =IF(Lists!D10="","",Lists!D10) -> G&B PRINTING PRESS AND BUSINESS CENTER | C20: =IF(B20="","",IFERROR(INDEX('MD Register'!C$5:C$104,MATCH(B20,'MD Register'!B$5:B$104,0)),"")) -> CRM | D20: =IF(B20="","",IFERROR(INDEX('MD Register'!D$5:D$104,MATCH(B20,'MD Register'!B$5:B$104,0)),"")) -> LCCH SEC 1&2 | E20: =IF(B20="","",SUMIF('MD Register'!$B$5:$B$104,TRIM(B20),'MD Register'!$F$5:$F$104)) -> 1514500 | F20: =IF(B20="","",SUMIF('MD Register'!$B$5:$B$104,TRIM(B20),'MD Register'!$V$5:$V$104)) -> 0 | G20: =IF(B20="","",SUMIF('MD Register'!$B$5:$B$104,TRIM(B20),'MD Register'!$AC$5:$AC$104)) -> 1514500 | H20: =IF(B20="","",E20-F20-G20) -> 0 | I20: =IF(OR(B20="",E20=0),"-",F20/E20) -> 0
A21: =IF(Lists!D11="","",10) -> 10 | B21: =IF(Lists!D11="","",Lists!D11) -> Lifeline Option Enterprises | C21: =IF(B21="","",IFERROR(INDEX('MD Register'!C$5:C$104,MATCH(B21,'MD Register'!B$5:B$104,0)),"")) -> CSR | D21: =IF(B21="","",IFERROR(INDEX('MD Register'!D$5:D$104,MATCH(B21,'MD Register'!B$5:B$104,0)),"")) -> LCCH SEC 1&2 | E21: =IF(B21="","",SUMIF('MD Register'!$B$5:$B$104,TRIM(B21),'MD Register'!$F$5:$F$104)) -> 1000000 | F21: =IF(B21="","",SUMIF('MD Register'!$B$5:$B$104,TRIM(B21),'MD Register'!$V$5:$V$104)) -> 790000 | G21: =IF(B21="","",SUMIF('MD Register'!$B$5:$B$104,TRIM(B21),'MD Register'!$AC$5:$AC$104)) -> 210000 | H21: =IF(B21="","",E21-F21-G21) -> 0 | I21: =IF(OR(B21="",E21=0),"-",F21/E21) -> 0.79
A22: =IF(Lists!D12="","",11) -> 11 | B22: =IF(Lists!D12="","",Lists!D12) -> CRM Office and SRAP Team | C22: =IF(B22="","",IFERROR(INDEX('MD Register'!C$5:C$104,MATCH(B22,'MD Register'!B$5:B$104,0)),"")) -> ESAP SEC 1 | D22: =IF(B22="","",IFERROR(INDEX('MD Register'!D$5:D$104,MATCH(B22,'MD Register'!B$5:B$104,0)),"")) -> LCCH SEC 1 | E22: =IF(B22="","",SUMIF('MD Register'!$B$5:$B$104,TRIM(B22),'MD Register'!$F$5:$F$104)) -> 872000 | F22: =IF(B22="","",SUMIF('MD Register'!$B$5:$B$104,TRIM(B22),'MD Register'!$V$5:$V$104)) -> 0 | G22: =IF(B22="","",SUMIF('MD Register'!$B$5:$B$104,TRIM(B22),'MD Register'!$AC$5:$AC$104)) -> 872000 | H22: =IF(B22="","",E22-F22-G22) -> 0 | I22: =IF(OR(B22="",E22=0),"-",F22/E22) -> 0
A23: =IF(Lists!D13="","",12) -> 12 | B23: =IF(Lists!D13="","",Lists!D13) -> EcoConserv | C23: =IF(B23="","",IFERROR(INDEX('MD Register'!C$5:C$104,MATCH(B23,'MD Register'!B$5:B$104,0)),"")) -> ESAP SEC 1 | D23: =IF(B23="","",IFERROR(INDEX('MD Register'!D$5:D$104,MATCH(B23,'MD Register'!B$5:B$104,0)),"")) -> LCCH SEC 1 | E23: =IF(B23="","",SUMIF('MD Register'!$B$5:$B$104,TRIM(B23),'MD Register'!$F$5:$F$104)) -> 24612600 | F23: =IF(B23="","",SUMIF('MD Register'!$B$5:$B$104,TRIM(B23),'MD Register'!$V$5:$V$104)) -> 7383780 | G23: =IF(B23="","",SUMIF('MD Register'!$B$5:$B$104,TRIM(B23),'MD Register'!$AC$5:$AC$104)) -> 9379015 | H23: =IF(B23="","",E23-F23-G23) -> 7849805 | I23: =IF(OR(B23="",E23=0),"-",F23/E23) -> 0.3
A24: =IF(Lists!D14="","",13) -> 13 | B24: =IF(Lists!D14="","",Lists!D14) -> Hitech CRM | C24: =IF(B24="","",IFERROR(INDEX('MD Register'!C$5:C$104,MATCH(B24,'MD Register'!B$5:B$104,0)),"")) | D24: =IF(B24="","",IFERROR(INDEX('MD Register'!D$5:D$104,MATCH(B24,'MD Register'!B$5:B$104,0)),"")) | E24: =IF(B24="","",SUMIF('MD Register'!$B$5:$B$104,TRIM(B24),'MD Register'!$F$5:$F$104)) -> 0 | F24: =IF(B24="","",SUMIF('MD Register'!$B$5:$B$104,TRIM(B24),'MD Register'!$V$5:$V$104)) -> 0 | G24: =IF(B24="","",SUMIF('MD Register'!$B$5:$B$104,TRIM(B24),'MD Register'!$AC$5:$AC$104)) -> 0 | H24: =IF(B24="","",E24-F24-G24) -> 0 | I24: =IF(OR(B24="",E24=0),"-",F24/E24) -> -
A25: =IF(Lists!D15="","",14) -> 14 | B25: =IF(Lists!D15="","",Lists!D15) -> Asili | C25: =IF(B25="","",IFERROR(INDEX('MD Register'!C$5:C$104,MATCH(B25,'MD Register'!B$5:B$104,0)),"")) | D25: =IF(B25="","",IFERROR(INDEX('MD Register'!D$5:D$104,MATCH(B25,'MD Register'!B$5:B$104,0)),"")) | E25: =IF(B25="","",SUMIF('MD Register'!$B$5:$B$104,TRIM(B25),'MD Register'!$F$5:$F$104)) -> 0 | F25: =IF(B25="","",SUMIF('MD Register'!$B$5:$B$104,TRIM(B25),'MD Register'!$V$5:$V$104)) -> 0 | G25: =IF(B25="","",SUMIF('MD Register'!$B$5:$B$104,TRIM(B25),'MD Register'!$AC$5:$AC$104)) -> 0 | H25: =IF(B25="","",E25-F25-G25) -> 0 | I25: =IF(OR(B25="",E25=0),"-",F25/E25) -> -
A26: =IF(Lists!D16="","",15) -> 15 | B26: =IF(Lists!D16="","",Lists!D16) -> Other | C26: =IF(B26="","",IFERROR(INDEX('MD Register'!C$5:C$104,MATCH(B26,'MD Register'!B$5:B$104,0)),"")) | D26: =IF(B26="","",IFERROR(INDEX('MD Register'!D$5:D$104,MATCH(B26,'MD Register'!B$5:B$104,0)),"")) | E26: =IF(B26="","",SUMIF('MD Register'!$B$5:$B$104,TRIM(B26),'MD Register'!$F$5:$F$104)) -> 0 | F26: =IF(B26="","",SUMIF('MD Register'!$B$5:$B$104,TRIM(B26),'MD Register'!$V$5:$V$104)) -> 0 | G26: =IF(B26="","",SUMIF('MD Register'!$B$5:$B$104,TRIM(B26),'MD Register'!$AC$5:$AC$104)) -> 0 | H26: =IF(B26="","",E26-F26-G26) -> 0 | I26: =IF(OR(B26="",E26=0),"-",F26/E26) -> -
A27: =IF(Lists!D17="","",16) | B27: =IF(Lists!D17="","",Lists!D17) | C27: =IF(B27="","",IFERROR(INDEX('MD Register'!C$5:C$104,MATCH(B27,'MD Register'!B$5:B$104,0)),"")) | D27: =IF(B27="","",IFERROR(INDEX('MD Register'!D$5:D$104,MATCH(B27,'MD Register'!B$5:B$104,0)),"")) | E27: =IF(B27="","",SUMIF('MD Register'!$B$5:$B$104,TRIM(B27),'MD Register'!$F$5:$F$104)) | F27: =IF(B27="","",SUMIF('MD Register'!$B$5:$B$104,TRIM(B27),'MD Register'!$V$5:$V$104)) | G27: =IF(B27="","",SUMIF('MD Register'!$B$5:$B$104,TRIM(B27),'MD Register'!$AC$5:$AC$104)) | H27: =IF(B27="","",E27-F27-G27) | I27: =IF(OR(B27="",E27=0),"-",F27/E27) -> -
A28: =IF(Lists!D18="","",17) | B28: =IF(Lists!D18="","",Lists!D18) | C28: =IF(B28="","",IFERROR(INDEX('MD Register'!C$5:C$104,MATCH(B28,'MD Register'!B$5:B$104,0)),"")) | D28: =IF(B28="","",IFERROR(INDEX('MD Register'!D$5:D$104,MATCH(B28,'MD Register'!B$5:B$104,0)),"")) | E28: =IF(B28="","",SUMIF('MD Register'!$B$5:$B$104,TRIM(B28),'MD Register'!$F$5:$F$104)) | F28: =IF(B28="","",SUMIF('MD Register'!$B$5:$B$104,TRIM(B28),'MD Register'!$V$5:$V$104)) | G28: =IF(B28="","",SUMIF('MD Register'!$B$5:$B$104,TRIM(B28),'MD Register'!$AC$5:$AC$104)) | H28: =IF(B28="","",E28-F28-G28) | I28: =IF(OR(B28="",E28=0),"-",F28/E28) -> -
A29: =IF(Lists!D19="","",18) | B29: =IF(Lists!D19="","",Lists!D19) | C29: =IF(B29="","",IFERROR(INDEX('MD Register'!C$5:C$104,MATCH(B29,'MD Register'!B$5:B$104,0)),"")) | D29: =IF(B29="","",IFERROR(INDEX('MD Register'!D$5:D$104,MATCH(B29,'MD Register'!B$5:B$104,0)),"")) | E29: =IF(B29="","",SUMIF('MD Register'!$B$5:$B$104,TRIM(B29),'MD Register'!$F$5:$F$104)) | F29: =IF(B29="","",SUMIF('MD Register'!$B$5:$B$104,TRIM(B29),'MD Register'!$V$5:$V$104)) | G29: =IF(B29="","",SUMIF('MD Register'!$B$5:$B$104,TRIM(B29),'MD Register'!$AC$5:$AC$104)) | H29: =IF(B29="","",E29-F29-G29) | I29: =IF(OR(B29="",E29=0),"-",F29/E29) -> -
A30: =IF(Lists!D20="","",19) | B30: =IF(Lists!D20="","",Lists!D20) | C30: =IF(B30="","",IFERROR(INDEX('MD Register'!C$5:C$104,MATCH(B30,'MD Register'!B$5:B$104,0)),"")) | D30: =IF(B30="","",IFERROR(INDEX('MD Register'!D$5:D$104,MATCH(B30,'MD Register'!B$5:B$104,0)),"")) | E30: =IF(B30="","",SUMIF('MD Register'!$B$5:$B$104,TRIM(B30),'MD Register'!$F$5:$F$104)) | F30: =IF(B30="","",SUMIF('MD Register'!$B$5:$B$104,TRIM(B30),'MD Register'!$V$5:$V$104)) | G30: =IF(B30="","",SUMIF('MD Register'!$B$5:$B$104,TRIM(B30),'MD Register'!$AC$5:$AC$104)) | H30: =IF(B30="","",E30-F30-G30) | I30: =IF(OR(B30="",E30=0),"-",F30/E30) -> -
A31: =IF(Lists!D21="","",20) | B31: =IF(Lists!D21="","",Lists!D21) | C31: =IF(B31="","",IFERROR(INDEX('MD Register'!C$5:C$104,MATCH(B31,'MD Register'!B$5:B$104,0)),"")) | D31: =IF(B31="","",IFERROR(INDEX('MD Register'!D$5:D$104,MATCH(B31,'MD Register'!B$5:B$104,0)),"")) | E31: =IF(B31="","",SUMIF('MD Register'!$B$5:$B$104,TRIM(B31),'MD Register'!$F$5:$F$104)) | F31: =IF(B31="","",SUMIF('MD Register'!$B$5:$B$104,TRIM(B31),'MD Register'!$V$5:$V$104)) | G31: =IF(B31="","",SUMIF('MD Register'!$B$5:$B$104,TRIM(B31),'MD Register'!$AC$5:$AC$104)) | H31: =IF(B31="","",E31-F31-G31) | I31: =IF(OR(B31="",E31=0),"-",F31/E31) -> -
A32: =IF(Lists!D22="","",21) | B32: =IF(Lists!D22="","",Lists!D22) | C32: =IF(B32="","",IFERROR(INDEX('MD Register'!C$5:C$104,MATCH(B32,'MD Register'!B$5:B$104,0)),"")) | D32: =IF(B32="","",IFERROR(INDEX('MD Register'!D$5:D$104,MATCH(B32,'MD Register'!B$5:B$104,0)),"")) | E32: =IF(B32="","",SUMIF('MD Register'!$B$5:$B$104,TRIM(B32),'MD Register'!$F$5:$F$104)) | F32: =IF(B32="","",SUMIF('MD Register'!$B$5:$B$104,TRIM(B32),'MD Register'!$V$5:$V$104)) | G32: =IF(B32="","",SUMIF('MD Register'!$B$5:$B$104,TRIM(B32),'MD Register'!$AC$5:$AC$104)) | H32: =IF(B32="","",E32-F32-G32) | I32: =IF(OR(B32="",E32=0),"-",F32/E32) -> -
A33: =IF(Lists!D23="","",22) | B33: =IF(Lists!D23="","",Lists!D23) | C33: =IF(B33="","",IFERROR(INDEX('MD Register'!C$5:C$104,MATCH(B33,'MD Register'!B$5:B$104,0)),"")) | D33: =IF(B33="","",IFERROR(INDEX('MD Register'!D$5:D$104,MATCH(B33,'MD Register'!B$5:B$104,0)),"")) | E33: =IF(B33="","",SUMIF('MD Register'!$B$5:$B$104,TRIM(B33),'MD Register'!$F$5:$F$104)) | F33: =IF(B33="","",SUMIF('MD Register'!$B$5:$B$104,TRIM(B33),'MD Register'!$V$5:$V$104)) | G33: =IF(B33="","",SUMIF('MD Register'!$B$5:$B$104,TRIM(B33),'MD Register'!$AC$5:$AC$104)) | H33: =IF(B33="","",E33-F33-G33) | I33: =IF(OR(B33="",E33=0),"-",F33/E33) -> -
A34: =IF(Lists!D24="","",23) | B34: =IF(Lists!D24="","",Lists!D24) | C34: =IF(B34="","",IFERROR(INDEX('MD Register'!C$5:C$104,MATCH(B34,'MD Register'!B$5:B$104,0)),"")) | D34: =IF(B34="","",IFERROR(INDEX('MD Register'!D$5:D$104,MATCH(B34,'MD Register'!B$5:B$104,0)),"")) | E34: =IF(B34="","",SUMIF('MD Register'!$B$5:$B$104,TRIM(B34),'MD Register'!$F$5:$F$104)) | F34: =IF(B34="","",SUMIF('MD Register'!$B$5:$B$104,TRIM(B34),'MD Register'!$V$5:$V$104)) | G34: =IF(B34="","",SUMIF('MD Register'!$B$5:$B$104,TRIM(B34),'MD Register'!$AC$5:$AC$104)) | H34: =IF(B34="","",E34-F34-G34) | I34: =IF(OR(B34="",E34=0),"-",F34/E34) -> -
A35: =IF(Lists!D25="","",24) | B35: =IF(Lists!D25="","",Lists!D25) | C35: =IF(B35="","",IFERROR(INDEX('MD Register'!C$5:C$104,MATCH(B35,'MD Register'!B$5:B$104,0)),"")) | D35: =IF(B35="","",IFERROR(INDEX('MD Register'!D$5:D$104,MATCH(B35,'MD Register'!B$5:B$104,0)),"")) | E35: =IF(B35="","",SUMIF('MD Register'!$B$5:$B$104,TRIM(B35),'MD Register'!$F$5:$F$104)) | F35: =IF(B35="","",SUMIF('MD Register'!$B$5:$B$104,TRIM(B35),'MD Register'!$V$5:$V$104)) | G35: =IF(B35="","",SUMIF('MD Register'!$B$5:$B$104,TRIM(B35),'MD Register'!$AC$5:$AC$104)) | H35: =IF(B35="","",E35-F35-G35) | I35: =IF(OR(B35="",E35=0),"-",F35/E35) -> -
A36: =IF(Lists!D26="","",25) | B36: =IF(Lists!D26="","",Lists!D26) | C36: =IF(B36="","",IFERROR(INDEX('MD Register'!C$5:C$104,MATCH(B36,'MD Register'!B$5:B$104,0)),"")) | D36: =IF(B36="","",IFERROR(INDEX('MD Register'!D$5:D$104,MATCH(B36,'MD Register'!B$5:B$104,0)),"")) | E36: =IF(B36="","",SUMIF('MD Register'!$B$5:$B$104,TRIM(B36),'MD Register'!$F$5:$F$104)) | F36: =IF(B36="","",SUMIF('MD Register'!$B$5:$B$104,TRIM(B36),'MD Register'!$V$5:$V$104)) | G36: =IF(B36="","",SUMIF('MD Register'!$B$5:$B$104,TRIM(B36),'MD Register'!$AC$5:$AC$104)) | H36: =IF(B36="","",E36-F36-G36) | I36: =IF(OR(B36="",E36=0),"-",F36/E36) -> -
A37: =IF(Lists!D27="","",26) | B37: =IF(Lists!D27="","",Lists!D27) | C37: =IF(B37="","",IFERROR(INDEX('MD Register'!C$5:C$104,MATCH(B37,'MD Register'!B$5:B$104,0)),"")) | D37: =IF(B37="","",IFERROR(INDEX('MD Register'!D$5:D$104,MATCH(B37,'MD Register'!B$5:B$104,0)),"")) | E37: =IF(B37="","",SUMIF('MD Register'!$B$5:$B$104,TRIM(B37),'MD Register'!$F$5:$F$104)) | F37: =IF(B37="","",SUMIF('MD Register'!$B$5:$B$104,TRIM(B37),'MD Register'!$V$5:$V$104)) | G37: =IF(B37="","",SUMIF('MD Register'!$B$5:$B$104,TRIM(B37),'MD Register'!$AC$5:$AC$104)) | H37: =IF(B37="","",E37-F37-G37) | I37: =IF(OR(B37="",E37=0),"-",F37/E37) -> -
A38: =IF(Lists!D28="","",27) | B38: =IF(Lists!D28="","",Lists!D28) | C38: =IF(B38="","",IFERROR(INDEX('MD Register'!C$5:C$104,MATCH(B38,'MD Register'!B$5:B$104,0)),"")) | D38: =IF(B38="","",IFERROR(INDEX('MD Register'!D$5:D$104,MATCH(B38,'MD Register'!B$5:B$104,0)),"")) | E38: =IF(B38="","",SUMIF('MD Register'!$B$5:$B$104,TRIM(B38),'MD Register'!$F$5:$F$104)) | F38: =IF(B38="","",SUMIF('MD Register'!$B$5:$B$104,TRIM(B38),'MD Register'!$V$5:$V$104)) | G38: =IF(B38="","",SUMIF('MD Register'!$B$5:$B$104,TRIM(B38),'MD Register'!$AC$5:$AC$104)) | H38: =IF(B38="","",E38-F38-G38) | I38: =IF(OR(B38="",E38=0),"-",F38/E38) -> -
A39: =IF(Lists!D29="","",28) | B39: =IF(Lists!D29="","",Lists!D29) | C39: =IF(B39="","",IFERROR(INDEX('MD Register'!C$5:C$104,MATCH(B39,'MD Register'!B$5:B$104,0)),"")) | D39: =IF(B39="","",IFERROR(INDEX('MD Register'!D$5:D$104,MATCH(B39,'MD Register'!B$5:B$104,0)),"")) | E39: =IF(B39="","",SUMIF('MD Register'!$B$5:$B$104,TRIM(B39),'MD Register'!$F$5:$F$104)) | F39: =IF(B39="","",SUMIF('MD Register'!$B$5:$B$104,TRIM(B39),'MD Register'!$V$5:$V$104)) | G39: =IF(B39="","",SUMIF('MD Register'!$B$5:$B$104,TRIM(B39),'MD Register'!$AC$5:$AC$104)) | H39: =IF(B39="","",E39-F39-G39) | I39: =IF(OR(B39="",E39=0),"-",F39/E39) -> -
A40: =IF(Lists!D30="","",29) | B40: =IF(Lists!D30="","",Lists!D30) | C40: =IF(B40="","",IFERROR(INDEX('MD Register'!C$5:C$104,MATCH(B40,'MD Register'!B$5:B$104,0)),"")) | D40: =IF(B40="","",IFERROR(INDEX('MD Register'!D$5:D$104,MATCH(B40,'MD Register'!B$5:B$104,0)),"")) | E40: =IF(B40="","",SUMIF('MD Register'!$B$5:$B$104,TRIM(B40),'MD Register'!$F$5:$F$104)) | F40: =IF(B40="","",SUMIF('MD Register'!$B$5:$B$104,TRIM(B40),'MD Register'!$V$5:$V$104)) | G40: =IF(B40="","",SUMIF('MD Register'!$B$5:$B$104,TRIM(B40),'MD Register'!$AC$5:$AC$104)) | H40: =IF(B40="","",E40-F40-G40) | I40: =IF(OR(B40="",E40=0),"-",F40/E40) -> -
A41: =IF(Lists!D31="","",30) | B41: =IF(Lists!D31="","",Lists!D31) | C41: =IF(B41="","",IFERROR(INDEX('MD Register'!C$5:C$104,MATCH(B41,'MD Register'!B$5:B$104,0)),"")) | D41: =IF(B41="","",IFERROR(INDEX('MD Register'!D$5:D$104,MATCH(B41,'MD Register'!B$5:B$104,0)),"")) | E41: =IF(B41="","",SUMIF('MD Register'!$B$5:$B$104,TRIM(B41),'MD Register'!$F$5:$F$104)) | F41: =IF(B41="","",SUMIF('MD Register'!$B$5:$B$104,TRIM(B41),'MD Register'!$V$5:$V$104)) | G41: =IF(B41="","",SUMIF('MD Register'!$B$5:$B$104,TRIM(B41),'MD Register'!$AC$5:$AC$104)) | H41: =IF(B41="","",E41-F41-G41) | I41: =IF(OR(B41="",E41=0),"-",F41/E41) -> -
A42: TOTAL | E42: =SUM(E12:E41) -> 7.4324317e+08 | F42: =SUM(F12:F41) -> 5.0819623e+08 | G42: =SUM(G12:G41) -> 22225515 | H42: =SUM(H12:H41) -> 2.1282142e+08 | I42: =IF(E42=0,0,F42/E42) -> 0.683755
A44: PROJECT COVERAGE
A45: # | B45: Project | C45: # Lines | D45: Contract (₦) | E45: Paid (₦) | F45: Pipeline (₦) | G45: % Paid
A46: 1 | B46: LCCH SEC 1 | C46: =COUNTIF('MD Register'!D$5:D$104,B46) -> 9 | D46: =SUMIF('MD Register'!D$5:D$104,B46,'MD Register'!F$5:F$104) -> 5.5988667e+08 | E46: =SUMIF('MD Register'!D$5:D$104,B46,'MD Register'!V$5:V$104) -> 3.6406008e+08 | F46: =SUMIF('MD Register'!D$5:D$104,B46,'MD Register'!AC$5:AC$104) -> 19479015 | G46: =IF(D46=0,"-",E46/D46) -> 0.65023887
A47: 2 | B47: LCCH SEC 1&2 | C47: =COUNTIF('MD Register'!D$5:D$104,B47) -> 20 | D47: =SUMIF('MD Register'!D$5:D$104,B47,'MD Register'!F$5:F$104) -> 192584496 | E47: =SUMIF('MD Register'!D$5:D$104,B47,'MD Register'!V$5:V$104) -> 1.4413615e+08 | F47: =SUMIF('MD Register'!D$5:D$104,B47,'MD Register'!AC$5:AC$104) -> 11974500 | G47: =IF(D47=0,"-",E47/D47) -> 0.74843072
A48: 3 | B48: LCCH SEC 2 | C48: =COUNTIF('MD Register'!D$5:D$104,B48) -> 0 | D48: =SUMIF('MD Register'!D$5:D$104,B48,'MD Register'!F$5:F$104) -> 0 | E48: =SUMIF('MD Register'!D$5:D$104,B48,'MD Register'!V$5:V$104) -> 0 | F48: =SUMIF('MD Register'!D$5:D$104,B48,'MD Register'!AC$5:AC$104) -> 0 | G48: =IF(D48=0,"-",E48/D48) -> -
A49: 4 | B49: LCCH SEC 3 | C49: =COUNTIF('MD Register'!D$5:D$104,B49) -> 0 | D49: =SUMIF('MD Register'!D$5:D$104,B49,'MD Register'!F$5:F$104) -> 0 | E49: =SUMIF('MD Register'!D$5:D$104,B49,'MD Register'!V$5:V$104) -> 0 | F49: =SUMIF('MD Register'!D$5:D$104,B49,'MD Register'!AC$5:AC$104) -> 0 | G49: =IF(D49=0,"-",E49/D49) -> -
A50: 5 | B50: LCCH SEC 4 | C50: =COUNTIF('MD Register'!D$5:D$104,B50) -> 0 | D50: =SUMIF('MD Register'!D$5:D$104,B50,'MD Register'!F$5:F$104) -> 0 | E50: =SUMIF('MD Register'!D$5:D$104,B50,'MD Register'!V$5:V$104) -> 0 | F50: =SUMIF('MD Register'!D$5:D$104,B50,'MD Register'!AC$5:AC$104) -> 0 | G50: =IF(D50=0,"-",E50/D50) -> -
A51: 6 | B51: LCCH SEC 5 | C51: =COUNTIF('MD Register'!D$5:D$104,B51) -> 0 | D51: =SUMIF('MD Register'!D$5:D$104,B51,'MD Register'!F$5:F$104) -> 0 | E51: =SUMIF('MD Register'!D$5:D$104,B51,'MD Register'!V$5:V$104) -> 0 | F51: =SUMIF('MD Register'!D$5:D$104,B51,'MD Register'!AC$5:AC$104) -> 0 | G51: =IF(D51=0,"-",E51/D51) -> -
A52: 7 | B52: SBS SOKOTO | C52: =COUNTIF('MD Register'!D$5:D$104,B52) -> 0 | D52: =SUMIF('MD Register'!D$5:D$104,B52,'MD Register'!F$5:F$104) -> 0 | E52: =SUMIF('MD Register'!D$5:D$104,B52,'MD Register'!V$5:V$104) -> 0 | F52: =SUMIF('MD Register'!D$5:D$104,B52,'MD Register'!AC$5:AC$104) -> 0 | G52: =IF(D52=0,"-",E52/D52) -> -
A53: 8 | B53: SBS KEBBI | C53: =COUNTIF('MD Register'!D$5:D$104,B53) -> 0 | D53: =SUMIF('MD Register'!D$5:D$104,B53,'MD Register'!F$5:F$104) -> 0 | E53: =SUMIF('MD Register'!D$5:D$104,B53,'MD Register'!V$5:V$104) -> 0 | F53: =SUMIF('MD Register'!D$5:D$104,B53,'MD Register'!AC$5:AC$104) -> 0 | G53: =IF(D53=0,"-",E53/D53) -> -
A54: 9 | B54: TRANS SAHARA | C54: =COUNTIF('MD Register'!D$5:D$104,B54) -> 0 | D54: =SUMIF('MD Register'!D$5:D$104,B54,'MD Register'!F$5:F$104) -> 0 | E54: =SUMIF('MD Register'!D$5:D$104,B54,'MD Register'!V$5:V$104) -> 0 | F54: =SUMIF('MD Register'!D$5:D$104,B54,'MD Register'!AC$5:AC$104) -> 0 | G54: =IF(D54=0,"-",E54/D54) -> -
A56: READ-ONLY DASHBOARD · All data entry in 'MD Register' only · Auto-refreshes from formulas
L57: Paid | M57: =C5 -> 5.0819623e+08
L58: Pipeline | M58: =E5 -> 31453515
L59: Unscheduled | M59: =G5 -> 2.1282142e+08
M81: =IF(B35="","",B35) | N81: =IF(B35="",0,F35) -> 0 | O81: =IF(B35="",0,G35) -> 0 | P81: =IF(B35="",0,H35) -> 0
M82: =IF(B36="","",B36) | N82: =IF(B36="",0,F36) -> 0 | O82: =IF(B36="",0,G36) -> 0 | P82: =IF(B36="",0,H36) -> 0
M83: =IF(B37="","",B37) | N83: =IF(B37="",0,F37) -> 0 | O83: =IF(B37="",0,G37) -> 0 | P83: =IF(B37="",0,H37) -> 0
M84: =IF(B38="","",B38) | N84: =IF(B38="",0,F38) -> 0 | O84: =IF(B38="",0,G38) -> 0 | P84: =IF(B38="",0,H38) -> 0
M85: =IF(B39="","",B39) | N85: =IF(B39="",0,F39) -> 0 | O85: =IF(B39="",0,G39) -> 0 | P85: =IF(B39="",0,H39) -> 0
M86: =IF(B40="","",B40) | N86: =IF(B40="",0,F40) -> 0 | O86: =IF(B40="",0,G40) -> 0 | P86: =IF(B40="",0,H40) -> 0

Sheet MD Register
A1: PAYMENT REGISTER — ESAP & ESG SERVICE PROVIDERS
A2: Yellow cells = to be completed | White cells = auto-calculated | DATE = tranche paid (even approximate) | No date = pipeline/upcoming | All amounts in ₦
A3: # | B3: Service Provider | C3: Category | D3: Project | E3: Description | F3: Contract Amount (₦) | G3: TRANCHE 1 | J3: TRANCHE 2 | M3: TRANCHE 3 | P3: TRANCHE 4 | S3: ONE-SHOT | V3: Total Paid (₦) | W3: Balance (₦) | X3: % Paid | Y3: Status | Z3: Invoice # | AA3: Contract # | AB3: Notes | AC3: Pipeline (₦)
G4: Amount (₦) | H4: Date | I4: Ref/POP | J4: Amount (₦) | K4: Date | L4: Ref/POP | M4: Amount (₦) | N4: Date | O4: Ref/POP | P4: Amount (₦) | Q4: Date | R4: Ref/POP | S4: Amount (₦) | T4: Date | U4: Ref/POP | Z4: Ref | AA4: Ref | AB4: Details | AC4: À VENIR
A5: =IF(B5="","",ROW()-4) -> 1 | B5: NCF | C5: ESAP-BMP | D5: LCCH SEC 1&2 | E5: BMP Implementation Phase 1+ 2 | F5: 82934896 | G5: 14546700 | H5: =DATE(2025,10,20) -> 45950 | I5: POP Access Bank | J5: 47717620 | K5: 46063 | V5: =IF(TRIM(Y5)="PAID",SUM(G5,J5,M5,P5,S5),IF(AND(H5<>"",LEN(TRIM(H5))>0),G5,0)+IF(AND(K5<>"",LEN(TRIM(K5))>0),J5,0)+IF(AND(N5<>"",LEN(TRIM(N5))>0),M5,0)+IF(AND(Q5<>"",LEN(TRIM(Q5))>0),P5,0)+IF(AND(T5<>"",LEN(TRIM(T5))>0),S5,0)) -> 62264320 | W5: =IF(OR(F5="",F5=0),"",MAX(0,F5-V5-AC5)) -> 20670576 | X5: =IF(OR(F5=0,F5=""),"-",V5/F5) -> 0.75076142 | Y5: PARTIAL | Z5: 0120054 / 0120065 | AB5: POP Access Bank | AC5: =IF(TRIM(Y5)="PAID",0,IF((IF(AND(OR(H5="",LEN(TRIM(H5))=0),ISNUMBER(G5),G5>0),G5,0)+IF(AND(OR(K5="",LEN(TRIM(K5))=0),ISNUMBER(J5),J5>0),J5,0)+IF(AND(OR(N5="",LEN(TRIM(N5))=0),ISNUMBER(M5),M5>0),M5,0)+IF(AND(OR(Q5="",LEN(TRIM(Q5))=0),ISNUMBER(P5),P5>0),P5,0)+IF(AND(OR(T5="",LEN(TRIM(T5))=0),ISNUMBER(S5),S5>0),S5,0))>0,IF(AND(OR(H5="",LEN(TRIM(H5))=0),ISNUMBER(G5),G5>0),G5,0)+IF(AND(OR(K5="",LEN(TRIM(K5))=0),ISNUMBER(J5),J5>0),J5,0)+IF(AND(OR(N5="",LEN(TRIM(N5))=0),ISNUMBER(M5),M5>0),M5,0)+IF(AND(OR(Q5="",LEN(TRIM(Q5))=0),ISNUMBER(P5),P5>0),P5,0)+IF(AND(OR(T5="",LEN(TRIM(T5))=0),ISNUMBER(S5),S5>0),S5,0),IF(OR(TRIM(Y5)="UPCOMING",TRIM(Y5)="PENDING"),MAX(0,F5-V5),0))) -> 0
A6: =IF(B6="","",ROW()-4) -> 2 | B6: DynaSmart | C6: ESAP-SRAP | D6: LCCH SEC 1 | E6: SRAP - Contract signing (35%) + Inception Report (30%) | F6: 4.5419667e+08 | G6: 158970000 | H6: 45992 | J6: 1.361282e+08 | K6: 46063 | V6: =IF(TRIM(Y6)="PAID",SUM(G6,J6,M6,P6,S6),IF(AND(H6<>"",LEN(TRIM(H6))>0),G6,0)+IF(AND(K6<>"",LEN(TRIM(K6))>0),J6,0)+IF(AND(N6<>"",LEN(TRIM(N6))>0),M6,0)+IF(AND(Q6<>"",LEN(TRIM(Q6))>0),P6,0)+IF(AND(T6<>"",LEN(TRIM(T6))>0),S6,0)) -> 2.950982e+08 | W6: =IF(OR(F6="",F6=0),"",MAX(0,F6-V6-AC6)) -> 1.5909847e+08 | X6: =IF(OR(F6=0,F6=""),"-",V6/F6) -> 0.64971458 | Y6: PARTIAL | Z6: 101 / 102 | AA6: HCCL/HO/CON-CA/25/004 | AB6: USD $110,141.40 - NGN TBC (T1) | AC6: =IF(TRIM(Y6)="PAID",0,IF((IF(AND(OR(H6="",LEN(TRIM(H6))=0),ISNUMBER(G6),G6>0),G6,0)+IF(AND(OR(K6="",LEN(TRIM(K6))=0),ISNUMBER(J6),J6>0),J6,0)+IF(AND(OR(N6="",LEN(TRIM(N6))=0),ISNUMBER(M6),M6>0),M6,0)+IF(AND(OR(Q6="",LEN(TRIM(Q6))=0),ISNUMBER(P6),P6>0),P6,0)+IF(AND(OR(T6="",LEN(TRIM(T6))=0),ISNUMBER(S6),S6>0),S6,0))>0,IF(AND(OR(H6="",LEN(TRIM(H6))=0),ISNUMBER(G6),G6>0),G6,0)+IF(AND(OR(K6="",LEN(TRIM(K6))=0),ISNUMBER(J6),J6>0),J6,0)+IF(AND(OR(N6="",LEN(TRIM(N6))=0),ISNUMBER(M6),M6>0),M6,0)+IF(AND(OR(Q6="",LEN(TRIM(Q6))=0),ISNUMBER(P6),P6>0),P6,0)+IF(AND(OR(T6="",LEN(TRIM(T6))=0),ISNUMBER(S6),S6>0),S6,0),IF(OR(TRIM(Y6)="UPCOMING",TRIM(Y6)="PENDING"),MAX(0,F6-V6),0))) -> 0
A7: =IF(B7="","",ROW()-4) -> 3 | B7: CEO Advisory | C7: HRRA | D7: LCCH SEC 1 | E7: Mobilization (30%) + Draft Report 30% | F7: 10050000 | G7: 3015000 | H7: 45874 | I7: POP FirstBank | J7: 3015000 | K7: 46063 | V7: =IF(TRIM(Y7)="PAID",SUM(G7,J7,M7,P7,S7),IF(AND(H7<>"",LEN(TRIM(H7))>0),G7,0)+IF(AND(K7<>"",LEN(TRIM(K7))>0),J7,0)+IF(AND(N7<>"",LEN(TRIM(N7))>0),M7,0)+IF(AND(Q7<>"",LEN(TRIM(Q7))>0),P7,0)+IF(AND(T7<>"",LEN(TRIM(T7))>0),S7,0)) -> 6030000 | W7: =IF(OR(F7="",F7=0),"",MAX(0,F7-V7-AC7)) -> 4020000 | X7: =IF(OR(F7=0,F7=""),"-",V7/F7) -> 0.6 | Y7: PARTIAL | AB7: POP FirstBank | AC7: =IF(TRIM(Y7)="PAID",0,IF((IF(AND(OR(H7="",LEN(TRIM(H7))=0),ISNUMBER(G7),G7>0),G7,0)+IF(AND(OR(K7="",LEN(TRIM(K7))=0),ISNUMBER(J7),J7>0),J7,0)+IF(AND(OR(N7="",LEN(TRIM(N7))=0),ISNUMBER(M7),M7>0),M7,0)+IF(AND(OR(Q7="",LEN(TRIM(Q7))=0),ISNUMBER(P7),P7>0),P7,0)+IF(AND(OR(T7="",LEN(TRIM(T7))=0),ISNUMBER(S7),S7>0),S7,0))>0,IF(AND(OR(H7="",LEN(TRIM(H7))=0),ISNUMBER(G7),G7>0),G7,0)+IF(AND(OR(K7="",LEN(TRIM(K7))=0),ISNUMBER(J7),J7>0),J7,0)+IF(AND(OR(N7="",LEN(TRIM(N7))=0),ISNUMBER(M7),M7>0),M7,0)+IF(AND(OR(Q7="",LEN(TRIM(Q7))=0),ISNUMBER(P7),P7>0),P7,0)+IF(AND(OR(T7="",LEN(TRIM(T7))=0),ISNUMBER(S7),S7>0),S7,0),IF(OR(TRIM(Y7)="UPCOMING",TRIM(Y7)="PENDING"),MAX(0,F7-V7),0))) -> 0
A8: =IF(B8="","",ROW()-4) -> 4 | B8: Eddie Perez Limited | C8: OD SURVEY | D8: LCCH SEC 1 | E8: Mobilization fee for survey (60%) + Draft Report (30%) | F8: 53793000 | G8: 32275800 | H8: 45988 | J8: 16137900 | K8: 46063 | V8: =IF(TRIM(Y8)="PAID",SUM(G8,J8,M8,P8,S8),IF(AND(H8<>"",LEN(TRIM(H8))>0),G8,0)+IF(AND(K8<>"",LEN(TRIM(K8))>0),J8,0)+IF(AND(N8<>"",LEN(TRIM(N8))>0),M8,0)+IF(AND(Q8<>"",LEN(TRIM(Q8))>0),P8,0)+IF(AND(T8<>"",LEN(TRIM(T8))>0),S8,0)) -> 48413700 | W8: =IF(OR(F8="",F8=0),"",MAX(0,F8-V8-AC8)) -> 5379300 | X8: =IF(OR(F8=0,F8=""),"-",V8/F8) -> 0.9 | Y8: PARTIAL | Z8: INV-210126 | AB8: Next: Final 10% Q1 2026 | AC8: =IF(TRIM(Y8)="PAID",0,IF((IF(AND(OR(H8="",LEN(TRIM(H8))=0),ISNUMBER(G8),G8>0),G8,0)+IF(AND(OR(K8="",LEN(TRIM(K8))=0),ISNUMBER(J8),J8>0),J8,0)+IF(AND(OR(N8="",LEN(TRIM(N8))=0),ISNUMBER(M8),M8>0),M8,0)+IF(AND(OR(Q8="",LEN(TRIM(Q8))=0),ISNUMBER(P8),P8>0),P8,0)+IF(AND(OR(T8="",LEN(TRIM(T8))=0),ISNUMBER(S8),S8>0),S8,0))>0,IF(AND(OR(H8="",LEN(TRIM(H8))=0),ISNUMBER(G8),G8>0),G8,0)+IF(AND(OR(K8="",LEN(TRIM(K8))=0),ISNUMBER(J8),J8>0),J8,0)+IF(AND(OR(N8="",LEN(TRIM(N8))=0),ISNUMBER(M8),M8>0),M8,0)+IF(AND(OR(Q8="",LEN(TRIM(Q8))=0),ISNUMBER(P8),P8>0),P8,0)+IF(AND(OR(T8="",LEN(TRIM(T8))=0),ISNUMBER(S8),S8>0),S8,0),IF(OR(TRIM(Y8)="UPCOMING",TRIM(Y8)="PENDING"),MAX(0,F8-V8),0))) -> 0
A9: =IF(B9="","",ROW()-4) -> 5 | B9: Eddie Perez Limited | C9: SOCIO ECONOMIC SURVEYS | D9: LCCH SEC 1&2 | E9: Mobilization (50%) + Draft report (30%) | F9: 76871100 | G9: 38435550 | H9: =DATE(2026,1,6) -> 46028 | I9: TBC - Emile Antone | J9: 22632282 | K9: 46063 | V9: =IF(TRIM(Y9)="PAID",SUM(G9,J9,M9,P9,S9),IF(AND(H9<>"",LEN(TRIM(H9))>0),G9,0)+IF(AND(K9<>"",LEN(TRIM(K9))>0),J9,0)+IF(AND(N9<>"",LEN(TRIM(N9))>0),M9,0)+IF(AND(Q9<>"",LEN(TRIM(Q9))>0),P9,0)+IF(AND(T9<>"",LEN(TRIM(T9))>0),S9,0)) -> 61067832 | W9: =IF(OR(F9="",F9=0),"",MAX(0,F9-V9-AC9)) -> 15803268 | X9: =IF(OR(F9=0,F9=""),"-",V9/F9) -> 0.7944186 | Y9: PARTIAL | Z9: INV-260925 / INV-161225 | AB9: POP FirstBank | WHT deducted | Next: Final 20% Q1 2026 | AC9: =IF(TRIM(Y9)="PAID",0,IF((IF(AND(OR(H9="",LEN(TRIM(H9))=0),ISNUMBER(G9),G9>0),G9,0)+IF(AND(OR(K9="",LEN(TRIM(K9))=0),ISNUMBER(J9),J9>0),J9,0)+IF(AND(OR(N9="",LEN(TRIM(N9))=0),ISNUMBER(M9),M9>0),M9,0)+IF(AND(OR(Q9="",LEN(TRIM(Q9))=0),ISNUMBER(P9),P9>0),P9,0)+IF(AND(OR(T9="",LEN(TRIM(T9))=0),ISNUMBER(S9),S9>0),S9,0))>0,IF(AND(OR(H9="",LEN(TRIM(H9))=0),ISNUMBER(G9),G9>0),G9,0)+IF(AND(OR(K9="",LEN(TRIM(K9))=0),ISNUMBER(J9),J9>0),J9,0)+IF(AND(OR(N9="",LEN(TRIM(N9))=0),ISNUMBER(M9),M9>0),M9,0)+IF(AND(OR(Q9="",LEN(TRIM(Q9))=0),ISNUMBER(P9),P9>0),P9,0)+IF(AND(OR(T9="",LEN(TRIM(T9))=0),ISNUMBER(S9),S9>0),S9,0),IF(OR(TRIM(Y9)="UPCOMING",TRIM(Y9)="PENDING"),MAX(0,F9-V9),0))) -> 0
A10: =IF(B10="","",ROW()-4) -> 6 | B10: David Omaghomi | C10: CRM | D10: LCCH SEC 1&2 | E10: Communitiy Awareness Campaigns (June - Sept 2025) | F10: 1750000 | S10: 1750000 | T10: 45972 | V10: =IF(TRIM(Y10)="PAID",SUM(G10,J10,M10,P10,S10),IF(AND(H10<>"",LEN(TRIM(H10))>0),G10,0)+IF(AND(K10<>"",LEN(TRIM(K10))>0),J10,0)+IF(AND(N10<>"",LEN(TRIM(N10))>0),M10,0)+IF(AND(Q10<>"",LEN(TRIM(Q10))>0),P10,0)+IF(AND(T10<>"",LEN(TRIM(T10))>0),S10,0)) -> 1750000 | W10: =IF(OR(F10="",F10=0),"",MAX(0,F10-V10-AC10)) -> 0 | X10: =IF(OR(F10=0,F10=""),"-",V10/F10) -> 1 | Y10: PAID | Z10: — | AB10: TBC - Emile Antone | AC10: =IF(TRIM(Y10)="PAID",0,IF((IF(AND(OR(H10="",LEN(TRIM(H10))=0),ISNUMBER(G10),G10>0),G10,0)+IF(AND(OR(K10="",LEN(TRIM(K10))=0),ISNUMBER(J10),J10>0),J10,0)+IF(AND(OR(N10="",LEN(TRIM(N10))=0),ISNUMBER(M10),M10>0),M10,0)+IF(AND(OR(Q10="",LEN(TRIM(Q10))=0),ISNUMBER(P10),P10>0),P10,0)+IF(AND(OR(T10="",LEN(TRIM(T10))=0),ISNUMBER(S10),S10>0),S10,0))>0,IF(AND(OR(H10="",LEN(TRIM(H10))=0),ISNUMBER(G10),G10>0),G10,0)+IF(AND(OR(K10="",LEN(TRIM(K10))=0),ISNUMBER(J10),J10>0),J10,0)+IF(AND(OR(N10="",LEN(TRIM(N10))=0),ISNUMBER(M10),M10>0),M10,0)+IF(AND(OR(Q10="",LEN(TRIM(Q10))=0),ISNUMBER(P10),P10>0),P10,0)+IF(AND(OR(T10="",LEN(TRIM(T10))=0),ISNUMBER(S10),S10>0),S10,0),IF(OR(TRIM(Y10)="UPCOMING",TRIM(Y10)="PENDING"),MAX(0,F10-V10),0))) -> 0
A11: =IF(B11="","",ROW()-4) -> 7 | B11: Hitech-CRM | C11: ESAP SEC 1 | D11: LCCH SEC 1 | E11: GRC Activity | F11: 3964400 | S11: 3964400 | T11: 45965 | V11: =IF(TRIM(Y11)="PAID",SUM(G11,J11,M11,P11,S11),IF(AND(H11<>"",LEN(TRIM(H11))>0),G11,0)+IF(AND(K11<>"",LEN(TRIM(K11))>0),J11,0)+IF(AND(N11<>"",LEN(TRIM(N11))>0),M11,0)+IF(AND(Q11<>"",LEN(TRIM(Q11))>0),P11,0)+IF(AND(T11<>"",LEN(TRIM(T11))>0),S11,0)) -> 3964400 | W11: =IF(OR(F11="",F11=0),"",MAX(0,F11-V11-AC11)) -> 0 | X11: =IF(OR(F11=0,F11=""),"-",V11/F11) -> 1 | Y11: PAID | AC11: =IF(TRIM(Y11)="PAID",0,IF((IF(AND(OR(H11="",LEN(TRIM(H11))=0),ISNUMBER(G11),G11>0),G11,0)+IF(AND(OR(K11="",LEN(TRIM(K11))=0),ISNUMBER(J11),J11>0),J11,0)+IF(AND(OR(N11="",LEN(TRIM(N11))=0),ISNUMBER(M11),M11>0),M11,0)+IF(AND(OR(Q11="",LEN(TRIM(Q11))=0),ISNUMBER(P11),P11>0),P11,0)+IF(AND(OR(T11="",LEN(TRIM(T11))=0),ISNUMBER(S11),S11>0),S11,0))>0,IF(AND(OR(H11="",LEN(TRIM(H11))=0),ISNUMBER(G11),G11>0),G11,0)+IF(AND(OR(K11="",LEN(TRIM(K11))=0),ISNUMBER(J11),J11>0),J11,0)+IF(AND(OR(N11="",LEN(TRIM(N11))=0),ISNUMBER(M11),M11>0),M11,0)+IF(AND(OR(Q11="",LEN(TRIM(Q11))=0),ISNUMBER(P11),P11>0),P11,0)+IF(AND(OR(T11="",LEN(TRIM(T11))=0),ISNUMBER(S11),S11>0),S11,0),IF(OR(TRIM(Y11)="UPCOMING",TRIM(Y11)="PENDING"),MAX(0,F11-V11),0))) -> 0
A12: =IF(B12="","",ROW()-4) -> 8 | B12: Beachtv Media Limited | C12: CSR | D12: LCCH SEC 1 | E12: Photography Videography - Lagos City Marathon | F12: 120000 | S12: 120000 | V12: =IF(TRIM(Y12)="PAID",SUM(G12,J12,M12,P12,S12),IF(AND(H12<>"",LEN(TRIM(H12))>0),G12,0)+IF(AND(K12<>"",LEN(TRIM(K12))>0),J12,0)+IF(AND(N12<>"",LEN(TRIM(N12))>0),M12,0)+IF(AND(Q12<>"",LEN(TRIM(Q12))>0),P12,0)+IF(AND(T12<>"",LEN(TRIM(T12))>0),S12,0)) -> 120000 | W12: =IF(OR(F12="",F12=0),"",MAX(0,F12-V12-AC12)) -> 0 | X12: =IF(OR(F12=0,F12=""),"-",V12/F12) -> 1 | Y12: PAID | AC12: =IF(TRIM(Y12)="PAID",0,IF((IF(AND(OR(H12="",LEN(TRIM(H12))=0),ISNUMBER(G12),G12>0),G12,0)+IF(AND(OR(K12="",LEN(TRIM(K12))=0),ISNUMBER(J12),J12>0),J12,0)+IF(AND(OR(N12="",LEN(TRIM(N12))=0),ISNUMBER(M12),M12>0),M12,0)+IF(AND(OR(Q12="",LEN(TRIM(Q12))=0),ISNUMBER(P12),P12>0),P12,0)+IF(AND(OR(T12="",LEN(TRIM(T12))=0),ISNUMBER(S12),S12>0),S12,0))>0,IF(AND(OR(H12="",LEN(TRIM(H12))=0),ISNUMBER(G12),G12>0),G12,0)+IF(AND(OR(K12="",LEN(TRIM(K12))=0),ISNUMBER(J12),J12>0),J12,0)+IF(AND(OR(N12="",LEN(TRIM(N12))=0),ISNUMBER(M12),M12>0),M12,0)+IF(AND(OR(Q12="",LEN(TRIM(Q12))=0),ISNUMBER(P12),P12>0),P12,0)+IF(AND(OR(T12="",LEN(TRIM(T12))=0),ISNUMBER(S12),S12>0),S12,0),IF(OR(TRIM(Y12)="UPCOMING",TRIM(Y12)="PENDING"),MAX(0,F12-V12),0))) -> 0
A13: =IF(B13="","",ROW()-4) -> 9 | B13: David Omaghomi | C13: CRM | D13: LCCH SEC 1&2 | E13: Payment for Community Relation Manager retainer fee for 5 months (from June 2025 to October 2025) | F13: 10000000 | S13: 10000000 | T13: 45966 | V13: =IF(TRIM(Y13)="PAID",SUM(G13,J13,M13,P13,S13),IF(AND(H13<>"",LEN(TRIM(H13))>0),G13,0)+IF(AND(K13<>"",LEN(TRIM(K13))>0),J13,0)+IF(AND(N13<>"",LEN(TRIM(N13))>0),M13,0)+IF(AND(Q13<>"",LEN(TRIM(Q13))>0),P13,0)+IF(AND(T13<>"",LEN(TRIM(T13))>0),S13,0)) -> 10000000 | W13: =IF(OR(F13="",F13=0),"",MAX(0,F13-V13-AC13)) -> 0 | X13: =IF(OR(F13=0,F13=""),"-",V13/F13) -> 1 | Y13: PAID | AC13: =IF(TRIM(Y13)="PAID",0,IF((IF(AND(OR(H13="",LEN(TRIM(H13))=0),ISNUMBER(G13),G13>0),G13,0)+IF(AND(OR(K13="",LEN(TRIM(K13))=0),ISNUMBER(J13),J13>0),J13,0)+IF(AND(OR(N13="",LEN(TRIM(N13))=0),ISNUMBER(M13),M13>0),M13,0)+IF(AND(OR(Q13="",LEN(TRIM(Q13))=0),ISNUMBER(P13),P13>0),P13,0)+IF(AND(OR(T13="",LEN(TRIM(T13))=0),ISNUMBER(S13),S13>0),S13,0))>0,IF(AND(OR(H13="",LEN(TRIM(H13))=0),ISNUMBER(G13),G13>0),G13,0)+IF(AND(OR(K13="",LEN(TRIM(K13))=0),ISNUMBER(J13),J13>0),J13,0)+IF(AND(OR(N13="",LEN(TRIM(N13))=0),ISNUMBER(M13),M13>0),M13,0)+IF(AND(OR(Q13="",LEN(TRIM(Q13))=0),ISNUMBER(P13),P13>0),P13,0)+IF(AND(OR(T13="",LEN(TRIM(T13))=0),ISNUMBER(S13),S13>0),S13,0),IF(OR(TRIM(Y13)="UPCOMING",TRIM(Y13)="PENDING"),MAX(0,F13-V13),0))) -> 0
A14: =IF(B14="","",ROW()-4) -> 10 | B14: G&B PRINTING PRESS AND BUSINESS CENTER | C14: CRM | D14: LCCH SEC 1&2 | E14: Office supplies | F14: 300000 | T14: 46080 | V14: =IF(TRIM(Y14)="PAID",SUM(G14,J14,M14,P14,S14),IF(AND(H14<>"",LEN(TRIM(H14))>0),G14,0)+IF(AND(K14<>"",LEN(TRIM(K14))>0),J14,0)+IF(AND(N14<>"",LEN(TRIM(N14))>0),M14,0)+IF(AND(Q14<>"",LEN(TRIM(Q14))>0),P14,0)+IF(AND(T14<>"",LEN(TRIM(T14))>0),S14,0)) -> 0 | W14: =IF(OR(F14="",F14=0),"",MAX(0,F14-V14-AC14)) -> 0 | X14: =IF(OR(F14=0,F14=""),"-",V14/F14) -> 0 | Y14: PENDING | AC14: =IF(TRIM(Y14)="PAID",0,IF((IF(AND(OR(H14="",LEN(TRIM(H14))=0),ISNUMBER(G14),G14>0),G14,0)+IF(AND(OR(K14="",LEN(TRIM(K14))=0),ISNUMBER(J14),J14>0),J14,0)+IF(AND(OR(N14="",LEN(TRIM(N14))=0),ISNUMBER(M14),M14>0),M14,0)+IF(AND(OR(Q14="",LEN(TRIM(Q14))=0),ISNUMBER(P14),P14>0),P14,0)+IF(AND(OR(T14="",LEN(TRIM(T14))=0),ISNUMBER(S14),S14>0),S14,0))>0,IF(AND(OR(H14="",LEN(TRIM(H14))=0),ISNUMBER(G14),G14>0),G14,0)+IF(AND(OR(K14="",LEN(TRIM(K14))=0),ISNUMBER(J14),J14>0),J14,0)+IF(AND(OR(N14="",LEN(TRIM(N14))=0),ISNUMBER(M14),M14>0),M14,0)+IF(AND(OR(Q14="",LEN(TRIM(Q14))=0),ISNUMBER(P14),P14>0),P14,0)+IF(AND(OR(T14="",LEN(TRIM(T14))=0),ISNUMBER(S14),S14>0),S14,0),IF(OR(TRIM(Y14)="UPCOMING",TRIM(Y14)="PENDING"),MAX(0,F14-V14),0))) -> 300000
A15: =IF(B15="","",ROW()-4) -> 11 | B15: G&B PRINTING PRESS AND BUSINESS CENTER | C15: CRM | D15: LCCH SEC 1&2 | E15: Office supplies | F15: 468000 | T15: 46065 | V15: =IF(TRIM(Y15)="PAID",SUM(G15,J15,M15,P15,S15),IF(AND(H15<>"",LEN(TRIM(H15))>0),G15,0)+IF(AND(K15<>"",LEN(TRIM(K15))>0),J15,0)+IF(AND(N15<>"",LEN(TRIM(N15))>0),M15,0)+IF(AND(Q15<>"",LEN(TRIM(Q15))>0),P15,0)+IF(AND(T15<>"",LEN(TRIM(T15))>0),S15,0)) -> 0 | W15: =IF(OR(F15="",F15=0),"",MAX(0,F15-V15-AC15)) -> 0 | X15: =IF(OR(F15=0,F15=""),"-",V15/F15) -> 0 | Y15: PENDING | AC15: =IF(TRIM(Y15)="PAID",0,IF((IF(AND(OR(H15="",LEN(TRIM(H15))=0),ISNUMBER(G15),G15>0),G15,0)+IF(AND(OR(K15="",LEN(TRIM(K15))=0),ISNUMBER(J15),J15>0),J15,0)+IF(AND(OR(N15="",LEN(TRIM(N15))=0),ISNUMBER(M15),M15>0),M15,0)+IF(AND(OR(Q15="",LEN(TRIM(Q15))=0),ISNUMBER(P15),P15>0),P15,0)+IF(AND(OR(T15="",LEN(TRIM(T15))=0),ISNUMBER(S15),S15>0),S15,0))>0,IF(AND(OR(H15="",LEN(TRIM(H15))=0),ISNUMBER(G15),G15>0),G15,0)+IF(AND(OR(K15="",LEN(TRIM(K15))=0),ISNUMBER(J15),J15>0),J15,0)+IF(AND(OR(N15="",LEN(TRIM(N15))=0),ISNUMBER(M15),M15>0),M15,0)+IF(AND(OR(Q15="",LEN(TRIM(Q15))=0),ISNUMBER(P15),P15>0),P15,0)+IF(AND(OR(T15="",LEN(TRIM(T15))=0),ISNUMBER(S15),S15>0),S15,0),IF(OR(TRIM(Y15)="UPCOMING",TRIM(Y15)="PENDING"),MAX(0,F15-V15),0))) -> 468000
A16: =IF(B16="","",ROW()-4) -> 12 | B16: G&B PRINTING PRESS AND BUSINESS CENTER | C16: CRM | D16: LCCH SEC 1&2 | E16: Office supplies | F16: 446500 | T16: 46021 | V16: =IF(TRIM(Y16)="PAID",SUM(G16,J16,M16,P16,S16),IF(AND(H16<>"",LEN(TRIM(H16))>0),G16,0)+IF(AND(K16<>"",LEN(TRIM(K16))>0),J16,0)+IF(AND(N16<>"",LEN(TRIM(N16))>0),M16,0)+IF(AND(Q16<>"",LEN(TRIM(Q16))>0),P16,0)+IF(AND(T16<>"",LEN(TRIM(T16))>0),S16,0)) -> 0 | W16: =IF(OR(F16="",F16=0),"",MAX(0,F16-V16-AC16)) -> 0 | X16: =IF(OR(F16=0,F16=""),"-",V16/F16) -> 0 | Y16: PENDING | AC16: =IF(TRIM(Y16)="PAID",0,IF((IF(AND(OR(H16="",LEN(TRIM(H16))=0),ISNUMBER(G16),G16>0),G16,0)+IF(AND(OR(K16="",LEN(TRIM(K16))=0),ISNUMBER(J16),J16>0),J16,0)+IF(AND(OR(N16="",LEN(TRIM(N16))=0),ISNUMBER(M16),M16>0),M16,0)+IF(AND(OR(Q16="",LEN(TRIM(Q16))=0),ISNUMBER(P16),P16>0),P16,0)+IF(AND(OR(T16="",LEN(TRIM(T16))=0),ISNUMBER(S16),S16>0),S16,0))>0,IF(AND(OR(H16="",LEN(TRIM(H16))=0),ISNUMBER(G16),G16>0),G16,0)+IF(AND(OR(K16="",LEN(TRIM(K16))=0),ISNUMBER(J16),J16>0),J16,0)+IF(AND(OR(N16="",LEN(TRIM(N16))=0),ISNUMBER(M16),M16>0),M16,0)+IF(AND(OR(Q16="",LEN(TRIM(Q16))=0),ISNUMBER(P16),P16>0),P16,0)+IF(AND(OR(T16="",LEN(TRIM(T16))=0),ISNUMBER(S16),S16>0),S16,0),IF(OR(TRIM(Y16)="UPCOMING",TRIM(Y16)="PENDING"),MAX(0,F16-V16),0))) -> 446500
A17: =IF(B17="","",ROW()-4) -> 13 | B17: Beachtv Media Limited | C17: CSR | D17: LCCH SEC 1&2 | E17: Photography - Videography - Drone Shoot | F17: 250000 | T17: 46032 | V17: =IF(TRIM(Y17)="PAID",SUM(G17,J17,M17,P17,S17),IF(AND(H17<>"",LEN(TRIM(H17))>0),G17,0)+IF(AND(K17<>"",LEN(TRIM(K17))>0),J17,0)+IF(AND(N17<>"",LEN(TRIM(N17))>0),M17,0)+IF(AND(Q17<>"",LEN(TRIM(Q17))>0),P17,0)+IF(AND(T17<>"",LEN(TRIM(T17))>0),S17,0)) -> 0 | W17: =IF(OR(F17="",F17=0),"",MAX(0,F17-V17-AC17)) -> 0 | X17: =IF(OR(F17=0,F17=""),"-",V17/F17) -> 0 | Y17: PENDING | AC17: =IF(TRIM(Y17)="PAID",0,IF((IF(AND(OR(H17="",LEN(TRIM(H17))=0),ISNUMBER(G17),G17>0),G17,0)+IF(AND(OR(K17="",LEN(TRIM(K17))=0),ISNUMBER(J17),J17>0),J17,0)+IF(AND(OR(N17="",LEN(TRIM(N17))=0),ISNUMBER(M17),M17>0),M17,0)+IF(AND(OR(Q17="",LEN(TRIM(Q17))=0),ISNUMBER(P17),P17>0),P17,0)+IF(AND(OR(T17="",LEN(TRIM(T17))=0),ISNUMBER(S17),S17>0),S17,0))>0,IF(AND(OR(H17="",LEN(TRIM(H17))=0),ISNUMBER(G17),G17>0),G17,0)+IF(AND(OR(K17="",LEN(TRIM(K17))=0),ISNUMBER(J17),J17>0),J17,0)+IF(AND(OR(N17="",LEN(TRIM(N17))=0),ISNUMBER(M17),M17>0),M17,0)+IF(AND(OR(Q17="",LEN(TRIM(Q17))=0),ISNUMBER(P17),P17>0),P17,0)+IF(AND(OR(T17="",LEN(TRIM(T17))=0),ISNUMBER(S17),S17>0),S17,0),IF(OR(TRIM(Y17)="UPCOMING",TRIM(Y17)="PENDING"),MAX(0,F17-V17),0))) -> 250000
A18: =IF(B18="","",ROW()-4) -> 14 | B18: G&B PRINTING PRESS AND BUSINESS CENTER | C18: CRM | D18: LCCH SEC 1&2 | E18: Office supplies | F18: 300000 | T18: 46000 | V18: =IF(TRIM(Y18)="PAID",SUM(G18,J18,M18,P18,S18),IF(AND(H18<>"",LEN(TRIM(H18))>0),G18,0)+IF(AND(K18<>"",LEN(TRIM(K18))>0),J18,0)+IF(AND(N18<>"",LEN(TRIM(N18))>0),M18,0)+IF(AND(Q18<>"",LEN(TRIM(Q18))>0),P18,0)+IF(AND(T18<>"",LEN(TRIM(T18))>0),S18,0)) -> 0 | W18: =IF(OR(F18="",F18=0),"",MAX(0,F18-V18-AC18)) -> 0 | X18: =IF(OR(F18=0,F18=""),"-",V18/F18) -> 0 | Y18: PENDING | AC18: =IF(TRIM(Y18)="PAID",0,IF((IF(AND(OR(H18="",LEN(TRIM(H18))=0),ISNUMBER(G18),G18>0),G18,0)+IF(AND(OR(K18="",LEN(TRIM(K18))=0),ISNUMBER(J18),J18>0),J18,0)+IF(AND(OR(N18="",LEN(TRIM(N18))=0),ISNUMBER(M18),M18>0),M18,0)+IF(AND(OR(Q18="",LEN(TRIM(Q18))=0),ISNUMBER(P18),P18>0),P18,0)+IF(AND(OR(T18="",LEN(TRIM(T18))=0),ISNUMBER(S18),S18>0),S18,0))>0,IF(AND(OR(H18="",LEN(TRIM(H18))=0),ISNUMBER(G18),G18>0),G18,0)+IF(AND(OR(K18="",LEN(TRIM(K18))=0),ISNUMBER(J18),J18>0),J18,0)+IF(AND(OR(N18="",LEN(TRIM(N18))=0),ISNUMBER(M18),M18>0),M18,0)+IF(AND(OR(Q18="",LEN(TRIM(Q18))=0),ISNUMBER(P18),P18>0),P18,0)+IF(AND(OR(T18="",LEN(TRIM(T18))=0),ISNUMBER(S18),S18>0),S18,0),IF(OR(TRIM(Y18)="UPCOMING",TRIM(Y18)="PENDING"),MAX(0,F18-V18),0))) -> 300000
A19: =IF(B19="","",ROW()-4) -> 15 | B19: Lifeline Option Enterprises | C19: CSR | D19: LCCH SEC 1&2 | E19: Adhoc staffs | F19: 40000 | S19: 40000 | T19: 45992 | V19: =IF(TRIM(Y19)="PAID",SUM(G19,J19,M19,P19,S19),IF(AND(H19<>"",LEN(TRIM(H19))>0),G19,0)+IF(AND(K19<>"",LEN(TRIM(K19))>0),J19,0)+IF(AND(N19<>"",LEN(TRIM(N19))>0),M19,0)+IF(AND(Q19<>"",LEN(TRIM(Q19))>0),P19,0)+IF(AND(T19<>"",LEN(TRIM(T19))>0),S19,0)) -> 40000 | W19: =IF(OR(F19="",F19=0),"",MAX(0,F19-V19-AC19)) -> 0 | X19: =IF(OR(F19=0,F19=""),"-",V19/F19) -> 1 | Y19: PAID | AC19: =IF(TRIM(Y19)="PAID",0,IF((IF(AND(OR(H19="",LEN(TRIM(H19))=0),ISNUMBER(G19),G19>0),G19,0)+IF(AND(OR(K19="",LEN(TRIM(K19))=0),ISNUMBER(J19),J19>0),J19,0)+IF(AND(OR(N19="",LEN(TRIM(N19))=0),ISNUMBER(M19),M19>0),M19,0)+IF(AND(OR(Q19="",LEN(TRIM(Q19))=0),ISNUMBER(P19),P19>0),P19,0)+IF(AND(OR(T19="",LEN(TRIM(T19))=0),ISNUMBER(S19),S19>0),S19,0))>0,IF(AND(OR(H19="",LEN(TRIM(H19))=0),ISNUMBER(G19),G19>0),G19,0)+IF(AND(OR(K19="",LEN(TRIM(K19))=0),ISNUMBER(J19),J19>0),J19,0)+IF(AND(OR(N19="",LEN(TRIM(N19))=0),ISNUMBER(M19),M19>0),M19,0)+IF(AND(OR(Q19="",LEN(TRIM(Q19))=0),ISNUMBER(P19),P19>0),P19,0)+IF(AND(OR(T19="",LEN(TRIM(T19))=0),ISNUMBER(S19),S19>0),S19,0),IF(OR(TRIM(Y19)="UPCOMING",TRIM(Y19)="PENDING"),MAX(0,F19-V19),0))) -> 0
A20: =IF(B20="","",ROW()-4) -> 16 | B20: Lifeline Option Enterprises | C20: CRM | D20: LCCH SEC 1&2 | E20: t | F20: 750000 | S20: 750000 | T20: 45966 | V20: =IF(TRIM(Y20)="PAID",SUM(G20,J20,M20,P20,S20),IF(AND(H20<>"",LEN(TRIM(H20))>0),G20,0)+IF(AND(K20<>"",LEN(TRIM(K20))>0),J20,0)+IF(AND(N20<>"",LEN(TRIM(N20))>0),M20,0)+IF(AND(Q20<>"",LEN(TRIM(Q20))>0),P20,0)+IF(AND(T20<>"",LEN(TRIM(T20))>0),S20,0)) -> 750000 | W20: =IF(OR(F20="",F20=0),"",MAX(0,F20-V20-AC20)) -> 0 | X20: =IF(OR(F20=0,F20=""),"-",V20/F20) -> 1 | Y20: PAID | AC20: =IF(TRIM(Y20)="PAID",0,IF((IF(AND(OR(H20="",LEN(TRIM(H20))=0),ISNUMBER(G20),G20>0),G20,0)+IF(AND(OR(K20="",LEN(TRIM(K20))=0),ISNUMBER(J20),J20>0),J20,0)+IF(AND(OR(N20="",LEN(TRIM(N20))=0),ISNUMBER(M20),M20>0),M20,0)+IF(AND(OR(Q20="",LEN(TRIM(Q20))=0),ISNUMBER(P20),P20>0),P20,0)+IF(AND(OR(T20="",LEN(TRIM(T20))=0),ISNUMBER(S20),S20>0),S20,0))>0,IF(AND(OR(H20="",LEN(TRIM(H20))=0),ISNUMBER(G20),G20>0),G20,0)+IF(AND(OR(K20="",LEN(TRIM(K20))=0),ISNUMBER(J20),J20>0),J20,0)+IF(AND(OR(N20="",LEN(TRIM(N20))=0),ISNUMBER(M20),M20>0),M20,0)+IF(AND(OR(Q20="",LEN(TRIM(Q20))=0),ISNUMBER(P20),P20>0),P20,0)+IF(AND(OR(T20="",LEN(TRIM(T20))=0),ISNUMBER(S20),S20>0),S20,0),IF(OR(TRIM(Y20)="UPCOMING",TRIM(Y20)="PENDING"),MAX(0,F20-V20),0))) -> 0
A21: =IF(B21="","",ROW()-4) -> 17 | B21: Lifeline Option Enterprises | C21: CRM | D21: LCCH SEC 1&2 | E21: Speaker hire - campaign | F21: 50000 | T21: 46000 | V21: =IF(TRIM(Y21)="PAID",SUM(G21,J21,M21,P21,S21),IF(AND(H21<>"",LEN(TRIM(H21))>0),G21,0)+IF(AND(K21<>"",LEN(TRIM(K21))>0),J21,0)+IF(AND(N21<>"",LEN(TRIM(N21))>0),M21,0)+IF(AND(Q21<>"",LEN(TRIM(Q21))>0),P21,0)+IF(AND(T21<>"",LEN(TRIM(T21))>0),S21,0)) -> 0 | W21: =IF(OR(F21="",F21=0),"",MAX(0,F21-V21-AC21)) -> 0 | X21: =IF(OR(F21=0,F21=""),"-",V21/F21) -> 0 | Y21: PENDING | AC21: =IF(TRIM(Y21)="PAID",0,IF((IF(AND(OR(H21="",LEN(TRIM(H21))=0),ISNUMBER(G21),G21>0),G21,0)+IF(AND(OR(K21="",LEN(TRIM(K21))=0),ISNUMBER(J21),J21>0),J21,0)+IF(AND(OR(N21="",LEN(TRIM(N21))=0),ISNUMBER(M21),M21>0),M21,0)+IF(AND(OR(Q21="",LEN(TRIM(Q21))=0),ISNUMBER(P21),P21>0),P21,0)+IF(AND(OR(T21="",LEN(TRIM(T21))=0),ISNUMBER(S21),S21>0),S21,0))>0,IF(AND(OR(H21="",LEN(TRIM(H21))=0),ISNUMBER(G21),G21>0),G21,0)+IF(AND(OR(K21="",LEN(TRIM(K21))=0),ISNUMBER(J21),J21>0),J21,0)+IF(AND(OR(N21="",LEN(TRIM(N21))=0),ISNUMBER(M21),M21>0),M21,0)+IF(AND(OR(Q21="",LEN(TRIM(Q21))=0),ISNUMBER(P21),P21>0),P21,0)+IF(AND(OR(T21="",LEN(TRIM(T21))=0),ISNUMBER(S21),S21>0),S21,0),IF(OR(TRIM(Y21)="UPCOMING",TRIM(Y21)="PENDING"),MAX(0,F21-V21),0))) -> 50000
A22: =IF(B22="","",ROW()-4) -> 18 | B22: Lifeline Option Enterprises | C22: CSR | D22: LCCH SEC 1&2 | E22: Adhoc staffs: Jan 10 to Feb 7. 2026 | F22: 120000 | V22: =IF(TRIM(Y22)="PAID",SUM(G22,J22,M22,P22,S22),IF(AND(H22<>"",LEN(TRIM(H22))>0),G22,0)+IF(AND(K22<>"",LEN(TRIM(K22))>0),J22,0)+IF(AND(N22<>"",LEN(TRIM(N22))>0),M22,0)+IF(AND(Q22<>"",LEN(TRIM(Q22))>0),P22,0)+IF(AND(T22<>"",LEN(TRIM(T22))>0),S22,0)) -> 0 | W22: =IF(OR(F22="",F22=0),"",MAX(0,F22-V22-AC22)) -> 0 | X22: =IF(OR(F22=0,F22=""),"-",V22/F22) -> 0 | Y22: PENDING | AC22: =IF(TRIM(Y22)="PAID",0,IF((IF(AND(OR(H22="",LEN(TRIM(H22))=0),ISNUMBER(G22),G22>0),G22,0)+IF(AND(OR(K22="",LEN(TRIM(K22))=0),ISNUMBER(J22),J22>0),J22,0)+IF(AND(OR(N22="",LEN(TRIM(N22))=0),ISNUMBER(M22),M22>0),M22,0)+IF(AND(OR(Q22="",LEN(TRIM(Q22))=0),ISNUMBER(P22),P22>0),P22,0)+IF(AND(OR(T22="",LEN(TRIM(T22))=0),ISNUMBER(S22),S22>0),S22,0))>0,IF(AND(OR(H22="",LEN(TRIM(H22))=0),ISNUMBER(G22),G22>0),G22,0)+IF(AND(OR(K22="",LEN(TRIM(K22))=0),ISNUMBER(J22),J22>0),J22,0)+IF(AND(OR(N22="",LEN(TRIM(N22))=0),ISNUMBER(M22),M22>0),M22,0)+IF(AND(OR(Q22="",LEN(TRIM(Q22))=0),ISNUMBER(P22),P22>0),P22,0)+IF(AND(OR(T22="",LEN(TRIM(T22))=0),ISNUMBER(S22),S22>0),S22,0),IF(OR(TRIM(Y22)="UPCOMING",TRIM(Y22)="PENDING"),MAX(0,F22-V22),0))) -> 120000
A23: =IF(B23="","",ROW()-4) -> 19 | B23: CRM Office and SRAP Team | C23: ESAP SEC 1 | D23: LCCH SEC 1 | E23: SRAP / GRC STAKEHOLDERS WORKSHOP MEETING 2026 | F23: 872000 | T23: 46116 | V23: =IF(TRIM(Y23)="PAID",SUM(G23,J23,M23,P23,S23),IF(AND(H23<>"",LEN(TRIM(H23))>0),G23,0)+IF(AND(K23<>"",LEN(TRIM(K23))>0),J23,0)+IF(AND(N23<>"",LEN(TRIM(N23))>0),M23,0)+IF(AND(Q23<>"",LEN(TRIM(Q23))>0),P23,0)+IF(AND(T23<>"",LEN(TRIM(T23))>0),S23,0)) -> 0 | W23: =IF(OR(F23="",F23=0),"",MAX(0,F23-V23-AC23)) -> 0 | X23: =IF(OR(F23=0,F23=""),"-",V23/F23) -> 0 | Y23: UPCOMING | AC23: =IF(TRIM(Y23)="PAID",0,IF((IF(AND(OR(H23="",LEN(TRIM(H23))=0),ISNUMBER(G23),G23>0),G23,0)+IF(AND(OR(K23="",LEN(TRIM(K23))=0),ISNUMBER(J23),J23>0),J23,0)+IF(AND(OR(N23="",LEN(TRIM(N23))=0),ISNUMBER(M23),M23>0),M23,0)+IF(AND(OR(Q23="",LEN(TRIM(Q23))=0),ISNUMBER(P23),P23>0),P23,0)+IF(AND(OR(T23="",LEN(TRIM(T23))=0),ISNUMBER(S23),S23>0),S23,0))>0,IF(AND(OR(H23="",LEN(TRIM(H23))=0),ISNUMBER(G23),G23>0),G23,0)+IF(AND(OR(K23="",LEN(TRIM(K23))=0),ISNUMBER(J23),J23>0),J23,0)+IF(AND(OR(N23="",LEN(TRIM(N23))=0),ISNUMBER(M23),M23>0),M23,0)+IF(AND(OR(Q23="",LEN(TRIM(Q23))=0),ISNUMBER(P23),P23>0),P23,0)+IF(AND(OR(T23="",LEN(TRIM(T23))=0),ISNUMBER(S23),S23>0),S23,0),IF(OR(TRIM(Y23)="UPCOMING",TRIM(Y23)="PENDING"),MAX(0,F23-V23),0))) -> 872000
A24: =IF(B24="","",ROW()-4) -> 20 | B24: David Omaghomi | C24: CRM | D24: LCCH SEC 1&2 | E24: Fuel (LSR 58 EZ) | F24: 610000 | S24: 610000 | T24: 46331 | V24: =IF(TRIM(Y24)="PAID",SUM(G24,J24,M24,P24,S24),IF(AND(H24<>"",LEN(TRIM(H24))>0),G24,0)+IF(AND(K24<>"",LEN(TRIM(K24))>0),J24,0)+IF(AND(N24<>"",LEN(TRIM(N24))>0),M24,0)+IF(AND(Q24<>"",LEN(TRIM(Q24))>0),P24,0)+IF(AND(T24<>"",LEN(TRIM(T24))>0),S24,0)) -> 610000 | W24: =IF(OR(F24="",F24=0),"",MAX(0,F24-V24-AC24)) -> 0 | X24: =IF(OR(F24=0,F24=""),"-",V24/F24) -> 1 | Y24: PAID | AC24: =IF(TRIM(Y24)="PAID",0,IF((IF(AND(OR(H24="",LEN(TRIM(H24))=0),ISNUMBER(G24),G24>0),G24,0)+IF(AND(OR(K24="",LEN(TRIM(K24))=0),ISNUMBER(J24),J24>0),J24,0)+IF(AND(OR(N24="",LEN(TRIM(N24))=0),ISNUMBER(M24),M24>0),M24,0)+IF(AND(OR(Q24="",LEN(TRIM(Q24))=0),ISNUMBER(P24),P24>0),P24,0)+IF(AND(OR(T24="",LEN(TRIM(T24))=0),ISNUMBER(S24),S24>0),S24,0))>0,IF(AND(OR(H24="",LEN(TRIM(H24))=0),ISNUMBER(G24),G24>0),G24,0)+IF(AND(OR(K24="",LEN(TRIM(K24))=0),ISNUMBER(J24),J24>0),J24,0)+IF(AND(OR(N24="",LEN(TRIM(N24))=0),ISNUMBER(M24),M24>0),M24,0)+IF(AND(OR(Q24="",LEN(TRIM(Q24))=0),ISNUMBER(P24),P24>0),P24,0)+IF(AND(OR(T24="",LEN(TRIM(T24))=0),ISNUMBER(S24),S24>0),S24,0),IF(OR(TRIM(Y24)="UPCOMING",TRIM(Y24)="PENDING"),MAX(0,F24-V24),0))) -> 0
A25: =IF(B25="","",ROW()-4) -> 21 | B25: David Omaghomi | C25: CRM | D25: LCCH SEC 1&2 | E25: April Pay for Community Relations Manager | F25: 2000000 | S25: 2000000 | T25: 45792 | V25: =IF(TRIM(Y25)="PAID",SUM(G25,J25,M25,P25,S25),IF(AND(H25<>"",LEN(TRIM(H25))>0),G25,0)+IF(AND(K25<>"",LEN(TRIM(K25))>0),J25,0)+IF(AND(N25<>"",LEN(TRIM(N25))>0),M25,0)+IF(AND(Q25<>"",LEN(TRIM(Q25))>0),P25,0)+IF(AND(T25<>"",LEN(TRIM(T25))>0),S25,0)) -> 2000000 | W25: =IF(OR(F25="",F25=0),"",MAX(0,F25-V25-AC25)) -> 0 | X25: =IF(OR(F25=0,F25=""),"-",V25/F25) -> 1 | Y25: PAID | AC25: =IF(TRIM(Y25)="PAID",0,IF((IF(AND(OR(H25="",LEN(TRIM(H25))=0),ISNUMBER(G25),G25>0),G25,0)+IF(AND(OR(K25="",LEN(TRIM(K25))=0),ISNUMBER(J25),J25>0),J25,0)+IF(AND(OR(N25="",LEN(TRIM(N25))=0),ISNUMBER(M25),M25>0),M25,0)+IF(AND(OR(Q25="",LEN(TRIM(Q25))=0),ISNUMBER(P25),P25>0),P25,0)+IF(AND(OR(T25="",LEN(TRIM(T25))=0),ISNUMBER(S25),S25>0),S25,0))>0,IF(AND(OR(H25="",LEN(TRIM(H25))=0),ISNUMBER(G25),G25>0),G25,0)+IF(AND(OR(K25="",LEN(TRIM(K25))=0),ISNUMBER(J25),J25>0),J25,0)+IF(AND(OR(N25="",LEN(TRIM(N25))=0),ISNUMBER(M25),M25>0),M25,0)+IF(AND(OR(Q25="",LEN(TRIM(Q25))=0),ISNUMBER(P25),P25>0),P25,0)+IF(AND(OR(T25="",LEN(TRIM(T25))=0),ISNUMBER(S25),S25>0),S25,0),IF(OR(TRIM(Y25)="UPCOMING",TRIM(Y25)="PENDING"),MAX(0,F25-V25),0))) -> 0
A26: =IF(B26="","",ROW()-4) -> 22 | B26: Ndoni Logistic | C26: CRM | D26: LCCH SEC 1&2 | E26: Provision of vehicule Hire (SUV) + Driver & Fueling | F26: 1600000 | S26: 1600000 | V26: =IF(TRIM(Y26)="PAID",SUM(G26,J26,M26,P26,S26),IF(AND(H26<>"",LEN(TRIM(H26))>0),G26,0)+IF(AND(K26<>"",LEN(TRIM(K26))>0),J26,0)+IF(AND(N26<>"",LEN(TRIM(N26))>0),M26,0)+IF(AND(Q26<>"",LEN(TRIM(Q26))>0),P26,0)+IF(AND(T26<>"",LEN(TRIM(T26))>0),S26,0)) -> 1600000 | W26: =IF(OR(F26="",F26=0),"",MAX(0,F26-V26-AC26)) -> 0 | X26: =IF(OR(F26=0,F26=""),"-",V26/F26) -> 1 | Y26: PAID | AC26: =IF(TRIM(Y26)="PAID",0,IF((IF(AND(OR(H26="",LEN(TRIM(H26))=0),ISNUMBER(G26),G26>0),G26,0)+IF(AND(OR(K26="",LEN(TRIM(K26))=0),ISNUMBER(J26),J26>0),J26,0)+IF(AND(OR(N26="",LEN(TRIM(N26))=0),ISNUMBER(M26),M26>0),M26,0)+IF(AND(OR(Q26="",LEN(TRIM(Q26))=0),ISNUMBER(P26),P26>0),P26,0)+IF(AND(OR(T26="",LEN(TRIM(T26))=0),ISNUMBER(S26),S26>0),S26,0))>0,IF(AND(OR(H26="",LEN(TRIM(H26))=0),ISNUMBER(G26),G26>0),G26,0)+IF(AND(OR(K26="",LEN(TRIM(K26))=0),ISNUMBER(J26),J26>0),J26,0)+IF(AND(OR(N26="",LEN(TRIM(N26))=0),ISNUMBER(M26),M26>0),M26,0)+IF(AND(OR(Q26="",LEN(TRIM(Q26))=0),ISNUMBER(P26),P26>0),P26,0)+IF(AND(OR(T26="",LEN(TRIM(T26))=0),ISNUMBER(S26),S26>0),S26,0),IF(OR(TRIM(Y26)="UPCOMING",TRIM(Y26)="PENDING"),MAX(0,F26-V26),0))) -> 0
A27: =IF(B27="","",ROW()-4) -> 23 | B27: David Omaghomi | C27: CRM | D27: LCCH SEC 1&2 | E27: Payment for Community Relation Manager | F27: 2554000 | S27: 2554000 | V27: =IF(TRIM(Y27)="PAID",SUM(G27,J27,M27,P27,S27),IF(AND(H27<>"",LEN(TRIM(H27))>0),G27,0)+IF(AND(K27<>"",LEN(TRIM(K27))>0),J27,0)+IF(AND(N27<>"",LEN(TRIM(N27))>0),M27,0)+IF(AND(Q27<>"",LEN(TRIM(Q27))>0),P27,0)+IF(AND(T27<>"",LEN(TRIM(T27))>0),S27,0)) -> 2554000 | W27: =IF(OR(F27="",F27=0),"",MAX(0,F27-V27-AC27)) -> 0 | X27: =IF(OR(F27=0,F27=""),"-",V27/F27) -> 1 | Y27: PAID | AC27: =IF(TRIM(Y27)="PAID",0,IF((IF(AND(OR(H27="",LEN(TRIM(H27))=0),ISNUMBER(G27),G27>0),G27,0)+IF(AND(OR(K27="",LEN(TRIM(K27))=0),ISNUMBER(J27),J27>0),J27,0)+IF(AND(OR(N27="",LEN(TRIM(N27))=0),ISNUMBER(M27),M27>0),M27,0)+IF(AND(OR(Q27="",LEN(TRIM(Q27))=0),ISNUMBER(P27),P27>0),P27,0)+IF(AND(OR(T27="",LEN(TRIM(T27))=0),ISNUMBER(S27),S27>0),S27,0))>0,IF(AND(OR(H27="",LEN(TRIM(H27))=0),ISNUMBER(G27),G27>0),G27,0)+IF(AND(OR(K27="",LEN(TRIM(K27))=0),ISNUMBER(J27),J27>0),J27,0)+IF(AND(OR(N27="",LEN(TRIM(N27))=0),ISNUMBER(M27),M27>0),M27,0)+IF(AND(OR(Q27="",LEN(TRIM(Q27))=0),ISNUMBER(P27),P27>0),P27,0)+IF(AND(OR(T27="",LEN(TRIM(T27))=0),ISNUMBER(S27),S27>0),S27,0),IF(OR(TRIM(Y27)="UPCOMING",TRIM(Y27)="PENDING"),MAX(0,F27-V27),0))) -> 0
A28: =IF(B28="","",ROW()-4) -> 24 | B28: Ndoni Logistic | C28: CRM | D28: LCCH SEC 1&2 | E28: Vehicule Hire- CRM Office June-July | F28: 1500000 | S28: 1500000 | T28: 45966 | V28: =IF(TRIM(Y28)="PAID",SUM(G28,J28,M28,P28,S28),IF(AND(H28<>"",LEN(TRIM(H28))>0),G28,0)+IF(AND(K28<>"",LEN(TRIM(K28))>0),J28,0)+IF(AND(N28<>"",LEN(TRIM(N28))>0),M28,0)+IF(AND(Q28<>"",LEN(TRIM(Q28))>0),P28,0)+IF(AND(T28<>"",LEN(TRIM(T28))>0),S28,0)) -> 1500000 | W28: =IF(OR(F28="",F28=0),"",MAX(0,F28-V28-AC28)) -> 0 | X28: =IF(OR(F28=0,F28=""),"-",V28/F28) -> 1 | Y28: PAID | AC28: =IF(TRIM(Y28)="PAID",0,IF((IF(AND(OR(H28="",LEN(TRIM(H28))=0),ISNUMBER(G28),G28>0),G28,0)+IF(AND(OR(K28="",LEN(TRIM(K28))=0),ISNUMBER(J28),J28>0),J28,0)+IF(AND(OR(N28="",LEN(TRIM(N28))=0),ISNUMBER(M28),M28>0),M28,0)+IF(AND(OR(Q28="",LEN(TRIM(Q28))=0),ISNUMBER(P28),P28>0),P28,0)+IF(AND(OR(T28="",LEN(TRIM(T28))=0),ISNUMBER(S28),S28>0),S28,0))>0,IF(AND(OR(H28="",LEN(TRIM(H28))=0),ISNUMBER(G28),G28>0),G28,0)+IF(AND(OR(K28="",LEN(TRIM(K28))=0),ISNUMBER(J28),J28>0),J28,0)+IF(AND(OR(N28="",LEN(TRIM(N28))=0),ISNUMBER(M28),M28>0),M28,0)+IF(AND(OR(Q28="",LEN(TRIM(Q28))=0),ISNUMBER(P28),P28>0),P28,0)+IF(AND(OR(T28="",LEN(TRIM(T28))=0),ISNUMBER(S28),S28>0),S28,0),IF(OR(TRIM(Y28)="UPCOMING",TRIM(Y28)="PENDING"),MAX(0,F28-V28),0))) -> 0
A29: =IF(B29="","",ROW()-4) -> 25 | B29: David Omaghomi | C29: CRM | D29: LCCH SEC 1 | E29: Payment for Community Relation Manager | F29: 3050000 | S29: 3050000 | T29: 45708 | V29: =IF(TRIM(Y29)="PAID",SUM(G29,J29,M29,P29,S29),IF(AND(H29<>"",LEN(TRIM(H29))>0),G29,0)+IF(AND(K29<>"",LEN(TRIM(K29))>0),J29,0)+IF(AND(N29<>"",LEN(TRIM(N29))>0),M29,0)+IF(AND(Q29<>"",LEN(TRIM(Q29))>0),P29,0)+IF(AND(T29<>"",LEN(TRIM(T29))>0),S29,0)) -> 3050000 | W29: =IF(OR(F29="",F29=0),"",MAX(0,F29-V29-AC29)) -> 0 | X29: =IF(OR(F29=0,F29=""),"-",V29/F29) -> 1 | Y29: PAID | AC29: =IF(TRIM(Y29)="PAID",0,IF((IF(AND(OR(H29="",LEN(TRIM(H29))=0),ISNUMBER(G29),G29>0),G29,0)+IF(AND(OR(K29="",LEN(TRIM(K29))=0),ISNUMBER(J29),J29>0),J29,0)+IF(AND(OR(N29="",LEN(TRIM(N29))=0),ISNUMBER(M29),M29>0),M29,0)+IF(AND(OR(Q29="",LEN(TRIM(Q29))=0),ISNUMBER(P29),P29>0),P29,0)+IF(AND(OR(T29="",LEN(TRIM(T29))=0),ISNUMBER(S29),S29>0),S29,0))>0,IF(AND(OR(H29="",LEN(TRIM(H29))=0),ISNUMBER(G29),G29>0),G29,0)+IF(AND(OR(K29="",LEN(TRIM(K29))=0),ISNUMBER(J29),J29>0),J29,0)+IF(AND(OR(N29="",LEN(TRIM(N29))=0),ISNUMBER(M29),M29>0),M29,0)+IF(AND(OR(Q29="",LEN(TRIM(Q29))=0),ISNUMBER(P29),P29>0),P29,0)+IF(AND(OR(T29="",LEN(TRIM(T29))=0),ISNUMBER(S29),S29>0),S29,0),IF(OR(TRIM(Y29)="UPCOMING",TRIM(Y29)="PENDING"),MAX(0,F29-V29),0))) -> 0
A30: =IF(B30="","",ROW()-4) -> 26 | B30: Lifeline Option Enterprises | C30: CSR | D30: LCCH SEC 1&2 | E30: Adhoc staffs 14 feb. 2026 | F30: 40000 | V30: =IF(TRIM(Y30)="PAID",SUM(G30,J30,M30,P30,S30),IF(AND(H30<>"",LEN(TRIM(H30))>0),G30,0)+IF(AND(K30<>"",LEN(TRIM(K30))>0),J30,0)+IF(AND(N30<>"",LEN(TRIM(N30))>0),M30,0)+IF(AND(Q30<>"",LEN(TRIM(Q30))>0),P30,0)+IF(AND(T30<>"",LEN(TRIM(T30))>0),S30,0)) -> 0 | W30: =IF(OR(F30="",F30=0),"",MAX(0,F30-V30-AC30)) -> 0 | X30: =IF(OR(F30=0,F30=""),"-",V30/F30) -> 0 | Y30: PENDING | AC30: =IF(TRIM(Y30)="PAID",0,IF((IF(AND(OR(H30="",LEN(TRIM(H30))=0),ISNUMBER(G30),G30>0),G30,0)+IF(AND(OR(K30="",LEN(TRIM(K30))=0),ISNUMBER(J30),J30>0),J30,0)+IF(AND(OR(N30="",LEN(TRIM(N30))=0),ISNUMBER(M30),M30>0),M30,0)+IF(AND(OR(Q30="",LEN(TRIM(Q30))=0),ISNUMBER(P30),P30>0),P30,0)+IF(AND(OR(T30="",LEN(TRIM(T30))=0),ISNUMBER(S30),S30>0),S30,0))>0,IF(AND(OR(H30="",LEN(TRIM(H30))=0),ISNUMBER(G30),G30>0),G30,0)+IF(AND(OR(K30="",LEN(TRIM(K30))=0),ISNUMBER(J30),J30>0),J30,0)+IF(AND(OR(N30="",LEN(TRIM(N30))=0),ISNUMBER(M30),M30>0),M30,0)+IF(AND(OR(Q30="",LEN(TRIM(Q30))=0),ISNUMBER(P30),P30>0),P30,0)+IF(AND(OR(T30="",LEN(TRIM(T30))=0),ISNUMBER(S30),S30>0),S30,0),IF(OR(TRIM(Y30)="UPCOMING",TRIM(Y30)="PENDING"),MAX(0,F30-V30),0))) -> 40000
A31: =IF(B31="","",ROW()-4) -> 27 | B31: David Omaghomi | C31: CRM | D31: LCCH SEC 1&2 | E31: Payment for CRM Office Nov 2025 to March 2026 | F31: 10000000 | V31: =IF(TRIM(Y31)="PAID",SUM(G31,J31,M31,P31,S31),IF(AND(H31<>"",LEN(TRIM(H31))>0),G31,0)+IF(AND(K31<>"",LEN(TRIM(K31))>0),J31,0)+IF(AND(N31<>"",LEN(TRIM(N31))>0),M31,0)+IF(AND(Q31<>"",LEN(TRIM(Q31))>0),P31,0)+IF(AND(T31<>"",LEN(TRIM(T31))>0),S31,0)) -> 0 | W31: =IF(OR(F31="",F31=0),"",MAX(0,F31-V31-AC31)) -> 0 | X31: =IF(OR(F31=0,F31=""),"-",V31/F31) -> 0 | Y31: PENDING | AC31: =IF(TRIM(Y31)="PAID",0,IF((IF(AND(OR(H31="",LEN(TRIM(H31))=0),ISNUMBER(G31),G31>0),G31,0)+IF(AND(OR(K31="",LEN(TRIM(K31))=0),ISNUMBER(J31),J31>0),J31,0)+IF(AND(OR(N31="",LEN(TRIM(N31))=0),ISNUMBER(M31),M31>0),M31,0)+IF(AND(OR(Q31="",LEN(TRIM(Q31))=0),ISNUMBER(P31),P31>0),P31,0)+IF(AND(OR(T31="",LEN(TRIM(T31))=0),ISNUMBER(S31),S31>0),S31,0))>0,IF(AND(OR(H31="",LEN(TRIM(H31))=0),ISNUMBER(G31),G31>0),G31,0)+IF(AND(OR(K31="",LEN(TRIM(K31))=0),ISNUMBER(J31),J31>0),J31,0)+IF(AND(OR(N31="",LEN(TRIM(N31))=0),ISNUMBER(M31),M31>0),M31,0)+IF(AND(OR(Q31="",LEN(TRIM(Q31))=0),ISNUMBER(P31),P31>0),P31,0)+IF(AND(OR(T31="",LEN(TRIM(T31))=0),ISNUMBER(S31),S31>0),S31,0),IF(OR(TRIM(Y31)="UPCOMING",TRIM(Y31)="PENDING"),MAX(0,F31-V31),0))) -> 10000000
A32: =IF(B32="","",ROW()-4) -> 28 | B32: EcoConserv | C32: ESAP SEC 1 | D32: LCCH SEC 1 | E32: HURRI - LCCH 30% | F32: 24612600 | G32: 7383780 | H32: 45903 | J32: 9379015 | L32: HURRI-LCCH 40% (à venir) | V32: =IF(TRIM(Y32)="PAID",SUM(G32,J32,M32,P32,S32),IF(AND(H32<>"",LEN(TRIM(H32))>0),G32,0)+IF(AND(K32<>"",LEN(TRIM(K32))>0),J32,0)+IF(AND(N32<>"",LEN(TRIM(N32))>0),M32,0)+IF(AND(Q32<>"",LEN(TRIM(Q32))>0),P32,0)+IF(AND(T32<>"",LEN(TRIM(T32))>0),S32,0)) -> 7383780 | W32: =IF(OR(F32="",F32=0),"",MAX(0,F32-V32-AC32)) -> 7849805 | X32: =IF(OR(F32=0,F32=""),"-",V32/F32) -> 0.3 | Y32: PARTIAL | AB32: 30% payé (T1) + 40% à venir (T2). Solde 30% restant. | AC32: =IF(TRIM(Y32)="PAID",0,IF((IF(AND(OR(H32="",LEN(TRIM(H32))=0),ISNUMBER(G32),G32>0),G32,0)+IF(AND(OR(K32="",LEN(TRIM(K32))=0),ISNUMBER(J32),J32>0),J32,0)+IF(AND(OR(N32="",LEN(TRIM(N32))=0),ISNUMBER(M32),M32>0),M32,0)+IF(AND(OR(Q32="",LEN(TRIM(Q32))=0),ISNUMBER(P32),P32>0),P32,0)+IF(AND(OR(T32="",LEN(TRIM(T32))=0),ISNUMBER(S32),S32>0),S32,0))>0,IF(AND(OR(H32="",LEN(TRIM(H32))=0),ISNUMBER(G32),G32>0),G32,0)+IF(AND(OR(K32="",LEN(TRIM(K32))=0),ISNUMBER(J32),J32>0),J32,0)+IF(AND(OR(N32="",LEN(TRIM(N32))=0),ISNUMBER(M32),M32>0),M32,0)+IF(AND(OR(Q32="",LEN(TRIM(Q32))=0),ISNUMBER(P32),P32>0),P32,0)+IF(AND(OR(T32="",LEN(TRIM(T32))=0),ISNUMBER(S32),S32>0),S32,0),IF(OR(TRIM(Y32)="UPCOMING",TRIM(Y32)="PENDING"),MAX(0,F32-V32),0))) -> 9379015
A33: =IF(B33="","",ROW()-4) -> 29 | B33: Hitech | C33: ESAP-SRAP | D33: LCCH SEC 1 | E33: SRAP/GRC Activities- April, 4, 2026 | F33: 9228000 | V33: =IF(TRIM(Y33)="PAID",SUM(G33,J33,M33,P33,S33),IF(AND(H33<>"",LEN(TRIM(H33))>0),G33,0)+IF(AND(K33<>"",LEN(TRIM(K33))>0),J33,0)+IF(AND(N33<>"",LEN(TRIM(N33))>0),M33,0)+IF(AND(Q33<>"",LEN(TRIM(Q33))>0),P33,0)+IF(AND(T33<>"",LEN(TRIM(T33))>0),S33,0)) -> 0 | W33: =IF(OR(F33="",F33=0),"",MAX(0,F33-V33-AC33)) -> 0 | X33: =IF(OR(F33=0,F33=""),"-",V33/F33) -> 0 | Y33: UPCOMING | AC33: =IF(TRIM(Y33)="PAID",0,IF((IF(AND(OR(H33="",LEN(TRIM(H33))=0),ISNUMBER(G33),G33>0),G33,0)+IF(AND(OR(K33="",LEN(TRIM(K33))=0),ISNUMBER(J33),J33>0),J33,0)+IF(AND(OR(N33="",LEN(TRIM(N33))=0),ISNUMBER(M33),M33>0),M33,0)+IF(AND(OR(Q33="",LEN(TRIM(Q33))=0),ISNUMBER(P33),P33>0),P33,0)+IF(AND(OR(T33="",LEN(TRIM(T33))=0),ISNUMBER(S33),S33>0),S33,0))>0,IF(AND(OR(H33="",LEN(TRIM(H33))=0),ISNUMBER(G33),G33>0),G33,0)+IF(AND(OR(K33="",LEN(TRIM(K33))=0),ISNUMBER(J33),J33>0),J33,0)+IF(AND(OR(N33="",LEN(TRIM(N33))=0),ISNUMBER(M33),M33>0),M33,0)+IF(AND(OR(Q33="",LEN(TRIM(Q33))=0),ISNUMBER(P33),P33>0),P33,0)+IF(AND(OR(T33="",LEN(TRIM(T33))=0),ISNUMBER(S33),S33>0),S33,0),IF(OR(TRIM(Y33)="UPCOMING",TRIM(Y33)="PENDING"),MAX(0,F33-V33),0))) -> 9228000
A34: =IF(B34="","",ROW()-4) | V34: =IF(TRIM(Y34)="PAID",SUM(G34,J34,M34,P34,S34),IF(AND(H34<>"",LEN(TRIM(H34))>0),G34,0)+IF(AND(K34<>"",LEN(TRIM(K34))>0),J34,0)+IF(AND(N34<>"",LEN(TRIM(N34))>0),M34,0)+IF(AND(Q34<>"",LEN(TRIM(Q34))>0),P34,0)+IF(AND(T34<>"",LEN(TRIM(T34))>0),S34,0)) -> 0 | W34: =IF(OR(F34="",F34=0),"",MAX(0,F34-V34-AC34)) | X34: =IF(OR(F34=0,F34=""),"-",V34/F34) -> - | AC34: =IF(TRIM(Y34)="PAID",0,IF((IF(AND(OR(H34="",LEN(TRIM(H34))=0),ISNUMBER(G34),G34>0),G34,0)+IF(AND(OR(K34="",LEN(TRIM(K34))=0),ISNUMBER(J34),J34>0),J34,0)+IF(AND(OR(N34="",LEN(TRIM(N34))=0),ISNUMBER(M34),M34>0),M34,0)+IF(AND(OR(Q34="",LEN(TRIM(Q34))=0),ISNUMBER(P34),P34>0),P34,0)+IF(AND(OR(T34="",LEN(TRIM(T34))=0),ISNUMBER(S34),S34>0),S34,0))>0,IF(AND(OR(H34="",LEN(TRIM(H34))=0),ISNUMBER(G34),G34>0),G34,0)+IF(AND(OR(K34="",LEN(TRIM(K34))=0),ISNUMBER(J34),J34>0),J34,0)+IF(AND(OR(N34="",LEN(TRIM(N34))=0),ISNUMBER(M34),M34>0),M34,0)+IF(AND(OR(Q34="",LEN(TRIM(Q34))=0),ISNUMBER(P34),P34>0),P34,0)+IF(AND(OR(T34="",LEN(TRIM(T34))=0),ISNUMBER(S34),S34>0),S34,0),IF(OR(TRIM(Y34)="UPCOMING",TRIM(Y34)="PENDING"),MAX(0,F34-V34),0))) -> 0
A35: =IF(B35="","",ROW()-4) | V35: =IF(TRIM(Y35)="PAID",SUM(G35,J35,M35,P35,S35),IF(AND(H35<>"",LEN(TRIM(H35))>0),G35,0)+IF(AND(K35<>"",LEN(TRIM(K35))>0),J35,0)+IF(AND(N35<>"",LEN(TRIM(N35))>0),M35,0)+IF(AND(Q35<>"",LEN(TRIM(Q35))>0),P35,0)+IF(AND(T35<>"",LEN(TRIM(T35))>0),S35,0)) -> 0 | W35: =IF(OR(F35="",F35=0),"",MAX(0,F35-V35-AC35)) | X35: =IF(OR(F35=0,F35=""),"-",V35/F35) -> - | AC35: =IF(TRIM(Y35)="PAID",0,IF((IF(AND(OR(H35="",LEN(TRIM(H35))=0),ISNUMBER(G35),G35>0),G35,0)+IF(AND(OR(K35="",LEN(TRIM(K35))=0),ISNUMBER(J35),J35>0),J35,0)+IF(AND(OR(N35="",LEN(TRIM(N35))=0),ISNUMBER(M35),M35>0),M35,0)+IF(AND(OR(Q35="",LEN(TRIM(Q35))=0),ISNUMBER(P35),P35>0),P35,0)+IF(AND(OR(T35="",LEN(TRIM(T35))=0),ISNUMBER(S35),S35>0),S35,0))>0,IF(AND(OR(H35="",LEN(TRIM(H35))=0),ISNUMBER(G35),G35>0),G35,0)+IF(AND(OR(K35="",LEN(TRIM(K35))=0),ISNUMBER(J35),J35>0),J35,0)+IF(AND(OR(N35="",LEN(TRIM(N35))=0),ISNUMBER(M35),M35>0),M35,0)+IF(AND(OR(Q35="",LEN(TRIM(Q35))=0),ISNUMBER(P35),P35>0),P35,0)+IF(AND(OR(T35="",LEN(TRIM(T35))=0),ISNUMBER(S35),S35>0),S35,0),IF(OR(TRIM(Y35)="UPCOMING",TRIM(Y35)="PENDING"),MAX(0,F35-V35),0))) -> 0
A36: =IF(B36="","",ROW()-4) | V36: =IF(TRIM(Y36)="PAID",SUM(G36,J36,M36,P36,S36),IF(AND(H36<>"",LEN(TRIM(H36))>0),G36,0)+IF(AND(K36<>"",LEN(TRIM(K36))>0),J36,0)+IF(AND(N36<>"",LEN(TRIM(N36))>0),M36,0)+IF(AND(Q36<>"",LEN(TRIM(Q36))>0),P36,0)+IF(AND(T36<>"",LEN(TRIM(T36))>0),S36,0)) -> 0 | W36: =IF(OR(F36="",F36=0),"",MAX(0,F36-V36-AC36)) | X36: =IF(OR(F36=0,F36=""),"-",V36/F36) -> - | AC36: =IF(TRIM(Y36)="PAID",0,IF((IF(AND(OR(H36="",LEN(TRIM(H36))=0),ISNUMBER(G36),G36>0),G36,0)+IF(AND(OR(K36="",LEN(TRIM(K36))=0),ISNUMBER(J36),J36>0),J36,0)+IF(AND(OR(N36="",LEN(TRIM(N36))=0),ISNUMBER(M36),M36>0),M36,0)+IF(AND(OR(Q36="",LEN(TRIM(Q36))=0),ISNUMBER(P36),P36>0),P36,0)+IF(AND(OR(T36="",LEN(TRIM(T36))=0),ISNUMBER(S36),S36>0),S36,0))>0,IF(AND(OR(H36="",LEN(TRIM(H36))=0),ISNUMBER(G36),G36>0),G36,0)+IF(AND(OR(K36="",LEN(TRIM(K36))=0),ISNUMBER(J36),J36>0),J36,0)+IF(AND(OR(N36="",LEN(TRIM(N36))=0),ISNUMBER(M36),M36>0),M36,0)+IF(AND(OR(Q36="",LEN(TRIM(Q36))=0),ISNUMBER(P36),P36>0),P36,0)+IF(AND(OR(T36="",LEN(TRIM(T36))=0),ISNUMBER(S36),S36>0),S36,0),IF(OR(TRIM(Y36)="UPCOMING",TRIM(Y36)="PENDING"),MAX(0,F36-V36),0))) -> 0
A37: =IF(B37="","",ROW()-4) | V37: =IF(TRIM(Y37)="PAID",SUM(G37,J37,M37,P37,S37),IF(AND(H37<>"",LEN(TRIM(H37))>0),G37,0)+IF(AND(K37<>"",LEN(TRIM(K37))>0),J37,0)+IF(AND(N37<>"",LEN(TRIM(N37))>0),M37,0)+IF(AND(Q37<>"",LEN(TRIM(Q37))>0),P37,0)+IF(AND(T37<>"",LEN(TRIM(T37))>0),S37,0)) -> 0 | W37: =IF(OR(F37="",F37=0),"",MAX(0,F37-V37-AC37)) | X37: =IF(OR(F37=0,F37=""),"-",V37/F37) -> - | AC37: =IF(TRIM(Y37)="PAID",0,IF((IF(AND(OR(H37="",LEN(TRIM(H37))=0),ISNUMBER(G37),G37>0),G37,0)+IF(AND(OR(K37="",LEN(TRIM(K37))=0),ISNUMBER(J37),J37>0),J37,0)+IF(AND(OR(N37="",LEN(TRIM(N37))=0),ISNUMBER(M37),M37>0),M37,0)+IF(AND(OR(Q37="",LEN(TRIM(Q37))=0),ISNUMBER(P37),P37>0),P37,0)+IF(AND(OR(T37="",LEN(TRIM(T37))=0),ISNUMBER(S37),S37>0),S37,0))>0,IF(AND(OR(H37="",LEN(TRIM(H37))=0),ISNUMBER(G37),G37>0),G37,0)+IF(AND(OR(K37="",LEN(TRIM(K37))=0),ISNUMBER(J37),J37>0),J37,0)+IF(AND(OR(N37="",LEN(TRIM(N37))=0),ISNUMBER(M37),M37>0),M37,0)+IF(AND(OR(Q37="",LEN(TRIM(Q37))=0),ISNUMBER(P37),P37>0),P37,0)+IF(AND(OR(T37="",LEN(TRIM(T37))=0),ISNUMBER(S37),S37>0),S37,0),IF(OR(TRIM(Y37)="UPCOMING",TRIM(Y37)="PENDING"),MAX(0,F37-V37),0))) -> 0
A38: =IF(B38="","",ROW()-4) | V38: =IF(TRIM(Y38)="PAID",SUM(G38,J38,M38,P38,S38),IF(AND(H38<>"",LEN(TRIM(H38))>0),G38,0)+IF(AND(K38<>"",LEN(TRIM(K38))>0),J38,0)+IF(AND(N38<>"",LEN(TRIM(N38))>0),M38,0)+IF(AND(Q38<>"",LEN(TRIM(Q38))>0),P38,0)+IF(AND(T38<>"",LEN(TRIM(T38))>0),S38,0)) -> 0 | W38: =IF(OR(F38="",F38=0),"",MAX(0,F38-V38-AC38)) | X38: =IF(OR(F38=0,F38=""),"-",V38/F38) -> - | AC38: =IF(TRIM(Y38)="PAID",0,IF((IF(AND(OR(H38="",LEN(TRIM(H38))=0),ISNUMBER(G38),G38>0),G38,0)+IF(AND(OR(K38="",LEN(TRIM(K38))=0),ISNUMBER(J38),J38>0),J38,0)+IF(AND(OR(N38="",LEN(TRIM(N38))=0),ISNUMBER(M38),M38>0),M38,0)+IF(AND(OR(Q38="",LEN(TRIM(Q38))=0),ISNUMBER(P38),P38>0),P38,0)+IF(AND(OR(T38="",LEN(TRIM(T38))=0),ISNUMBER(S38),S38>0),S38,0))>0,IF(AND(OR(H38="",LEN(TRIM(H38))=0),ISNUMBER(G38),G38>0),G38,0)+IF(AND(OR(K38="",LEN(TRIM(K38))=0),ISNUMBER(J38),J38>0),J38,0)+IF(AND(OR(N38="",LEN(TRIM(N38))=0),ISNUMBER(M38),M38>0),M38,0)+IF(AND(OR(Q38="",LEN(TRIM(Q38))=0),ISNUMBER(P38),P38>0),P38,0)+IF(AND(OR(T38="",LEN(TRIM(T38))=0),ISNUMBER(S38),S38>0),S38,0),IF(OR(TRIM(Y38)="UPCOMING",TRIM(Y38)="PENDING"),MAX(0,F38-V38),0))) -> 0
A39: =IF(B39="","",ROW()-4) | V39: =IF(TRIM(Y39)="PAID",SUM(G39,J39,M39,P39,S39),IF(AND(H39<>"",LEN(TRIM(H39))>0),G39,0)+IF(AND(K39<>"",LEN(TRIM(K39))>0),J39,0)+IF(AND(N39<>"",LEN(TRIM(N39))>0),M39,0)+IF(AND(Q39<>"",LEN(TRIM(Q39))>0),P39,0)+IF(AND(T39<>"",LEN(TRIM(T39))>0),S39,0)) -> 0 | W39: =IF(OR(F39="",F39=0),"",MAX(0,F39-V39-AC39)) | X39: =IF(OR(F39=0,F39=""),"-",V39/F39) -> - | AC39: =IF(TRIM(Y39)="PAID",0,IF((IF(AND(OR(H39="",LEN(TRIM(H39))=0),ISNUMBER(G39),G39>0),G39,0)+IF(AND(OR(K39="",LEN(TRIM(K39))=0),ISNUMBER(J39),J39>0),J39,0)+IF(AND(OR(N39="",LEN(TRIM(N39))=0),ISNUMBER(M39),M39>0),M39,0)+IF(AND(OR(Q39="",LEN(TRIM(Q39))=0),ISNUMBER(P39),P39>0),P39,0)+IF(AND(OR(T39="",LEN(TRIM(T39))=0),ISNUMBER(S39),S39>0),S39,0))>0,IF(AND(OR(H39="",LEN(TRIM(H39))=0),ISNUMBER(G39),G39>0),G39,0)+IF(AND(OR(K39="",LEN(TRIM(K39))=0),ISNUMBER(J39),J39>0),J39,0)+IF(AND(OR(N39="",LEN(TRIM(N39))=0),ISNUMBER(M39),M39>0),M39,0)+IF(AND(OR(Q39="",LEN(TRIM(Q39))=0),ISNUMBER(P39),P39>0),P39,0)+IF(AND(OR(T39="",LEN(TRIM(T39))=0),ISNUMBER(S39),S39>0),S39,0),IF(OR(TRIM(Y39)="UPCOMING",TRIM(Y39)="PENDING"),MAX(0,F39-V39),0))) -> 0
A40: =IF(B40="","",ROW()-4) | V40: =IF(TRIM(Y40)="PAID",SUM(G40,J40,M40,P40,S40),IF(AND(H40<>"",LEN(TRIM(H40))>0),G40,0)+IF(AND(K40<>"",LEN(TRIM(K40))>0),J40,0)+IF(AND(N40<>"",LEN(TRIM(N40))>0),M40,0)+IF(AND(Q40<>"",LEN(TRIM(Q40))>0),P40,0)+IF(AND(T40<>"",LEN(TRIM(T40))>0),S40,0)) -> 0 | W40: =IF(OR(F40="",F40=0),"",MAX(0,F40-V40-AC40)) | X40: =IF(OR(F40=0,F40=""),"-",V40/F40) -> - | AC40: =IF(TRIM(Y40)="PAID",0,IF((IF(AND(OR(H40="",LEN(TRIM(H40))=0),ISNUMBER(G40),G40>0),G40,0)+IF(AND(OR(K40="",LEN(TRIM(K40))=0),ISNUMBER(J40),J40>0),J40,0)+IF(AND(OR(N40="",LEN(TRIM(N40))=0),ISNUMBER(M40),M40>0),M40,0)+IF(AND(OR(Q40="",LEN(TRIM(Q40))=0),ISNUMBER(P40),P40>0),P40,0)+IF(AND(OR(T40="",LEN(TRIM(T40))=0),ISNUMBER(S40),S40>0),S40,0))>0,IF(AND(OR(H40="",LEN(TRIM(H40))=0),ISNUMBER(G40),G40>0),G40,0)+IF(AND(OR(K40="",LEN(TRIM(K40))=0),ISNUMBER(J40),J40>0),J40,0)+IF(AND(OR(N40="",LEN(TRIM(N40))=0),ISNUMBER(M40),M40>0),M40,0)+IF(AND(OR(Q40="",LEN(TRIM(Q40))=0),ISNUMBER(P40),P40>0),P40,0)+IF(AND(OR(T40="",LEN(TRIM(T40))=0),ISNUMBER(S40),S40>0),S40,0),IF(OR(TRIM(Y40)="UPCOMING",TRIM(Y40)="PENDING"),MAX(0,F40-V40),0))) -> 0
A41: =IF(B41="","",ROW()-4) | V41: =IF(TRIM(Y41)="PAID",SUM(G41,J41,M41,P41,S41),IF(AND(H41<>"",LEN(TRIM(H41))>0),G41,0)+IF(AND(K41<>"",LEN(TRIM(K41))>0),J41,0)+IF(AND(N41<>"",LEN(TRIM(N41))>0),M41,0)+IF(AND(Q41<>"",LEN(TRIM(Q41))>0),P41,0)+IF(AND(T41<>"",LEN(TRIM(T41))>0),S41,0)) -> 0 | W41: =IF(OR(F41="",F41=0),"",MAX(0,F41-V41-AC41)) | X41: =IF(OR(F41=0,F41=""),"-",V41/F41) -> - | AC41: =IF(TRIM(Y41)="PAID",0,IF((IF(AND(OR(H41="",LEN(TRIM(H41))=0),ISNUMBER(G41),G41>0),G41,0)+IF(AND(OR(K41="",LEN(TRIM(K41))=0),ISNUMBER(J41),J41>0),J41,0)+IF(AND(OR(N41="",LEN(TRIM(N41))=0),ISNUMBER(M41),M41>0),M41,0)+IF(AND(OR(Q41="",LEN(TRIM(Q41))=0),ISNUMBER(P41),P41>0),P41,0)+IF(AND(OR(T41="",LEN(TRIM(T41))=0),ISNUMBER(S41),S41>0),S41,0))>0,IF(AND(OR(H41="",LEN(TRIM(H41))=0),ISNUMBER(G41),G41>0),G41,0)+IF(AND(OR(K41="",LEN(TRIM(K41))=0),ISNUMBER(J41),J41>0),J41,0)+IF(AND(OR(N41="",LEN(TRIM(N41))=0),ISNUMBER(M41),M41>0),M41,0)+IF(AND(OR(Q41="",LEN(TRIM(Q41))=0),ISNUMBER(P41),P41>0),P41,0)+IF(AND(OR(T41="",LEN(TRIM(T41))=0),ISNUMBER(S41),S41>0),S41,0),IF(OR(TRIM(Y41)="UPCOMING",TRIM(Y41)="PENDING"),MAX(0,F41-V41),0))) -> 0
A42: =IF(B42="","",ROW()-4) | V42: =IF(TRIM(Y42)="PAID",SUM(G42,J42,M42,P42,S42),IF(AND(H42<>"",LEN(TRIM(H42))>0),G42,0)+IF(AND(K42<>"",LEN(TRIM(K42))>0),J42,0)+IF(AND(N42<>"",LEN(TRIM(N42))>0),M42,0)+IF(AND(Q42<>"",LEN(TRIM(Q42))>0),P42,0)+IF(AND(T42<>"",LEN(TRIM(T42))>0),S42,0)) -> 0 | W42: =IF(OR(F42="",F42=0),"",MAX(0,F42-V42-AC42)) | X42: =IF(OR(F42=0,F42=""),"-",V42/F42) -> - | AC42: =IF(TRIM(Y42)="PAID",0,IF((IF(AND(OR(H42="",LEN(TRIM(H42))=0),ISNUMBER(G42),G42>0),G42,0)+IF(AND(OR(K42="",LEN(TRIM(K42))=0),ISNUMBER(J42),J42>0),J42,0)+IF(AND(OR(N42="",LEN(TRIM(N42))=0),ISNUMBER(M42),M42>0),M42,0)+IF(AND(OR(Q42="",LEN(TRIM(Q42))=0),ISNUMBER(P42),P42>0),P42,0)+IF(AND(OR(T42="",LEN(TRIM(T42))=0),ISNUMBER(S42),S42>0),S42,0))>0,IF(AND(OR(H42="",LEN(TRIM(H42))=0),ISNUMBER(G42),G42>0),G42,0)+IF(AND(OR(K42="",LEN(TRIM(K42))=0),ISNUMBER(J42),J42>0),J42,0)+IF(AND(OR(N42="",LEN(TRIM(N42))=0),ISNUMBER(M42),M42>0),M42,0)+IF(AND(OR(Q42="",LEN(TRIM(Q42))=0),ISNUMBER(P42),P42>0),P42,0)+IF(AND(OR(T42="",LEN(TRIM(T42))=0),ISNUMBER(S42),S42>0),S42,0),IF(OR(TRIM(Y42)="UPCOMING",TRIM(Y42)="PENDING"),MAX(0,F42-V42),0))) -> 0
A43: =IF(B43="","",ROW()-4) | V43: =IF(TRIM(Y43)="PAID",SUM(G43,J43,M43,P43,S43),IF(AND(H43<>"",LEN(TRIM(H43))>0),G43,0)+IF(AND(K43<>"",LEN(TRIM(K43))>0),J43,0)+IF(AND(N43<>"",LEN(TRIM(N43))>0),M43,0)+IF(AND(Q43<>"",LEN(TRIM(Q43))>0),P43,0)+IF(AND(T43<>"",LEN(TRIM(T43))>0),S43,0)) -> 0 | W43: =IF(OR(F43="",F43=0),"",MAX(0,F43-V43-AC43)) | X43: =IF(OR(F43=0,F43=""),"-",V43/F43) -> - | AC43: =IF(TRIM(Y43)="PAID",0,IF((IF(AND(OR(H43="",LEN(TRIM(H43))=0),ISNUMBER(G43),G43>0),G43,0)+IF(AND(OR(K43="",LEN(TRIM(K43))=0),ISNUMBER(J43),J43>0),J43,0)+IF(AND(OR(N43="",LEN(TRIM(N43))=0),ISNUMBER(M43),M43>0),M43,0)+IF(AND(OR(Q43="",LEN(TRIM(Q43))=0),ISNUMBER(P43),P43>0),P43,0)+IF(AND(OR(T43="",LEN(TRIM(T43))=0),ISNUMBER(S43),S43>0),S43,0))>0,IF(AND(OR(H43="",LEN(TRIM(H43))=0),ISNUMBER(G43),G43>0),G43,0)+IF(AND(OR(K43="",LEN(TRIM(K43))=0),ISNUMBER(J43),J43>0),J43,0)+IF(AND(OR(N43="",LEN(TRIM(N43))=0),ISNUMBER(M43),M43>0),M43,0)+IF(AND(OR(Q43="",LEN(TRIM(Q43))=0),ISNUMBER(P43),P43>0),P43,0)+IF(AND(OR(T43="",LEN(TRIM(T43))=0),ISNUMBER(S43),S43>0),S43,0),IF(OR(TRIM(Y43)="UPCOMING",TRIM(Y43)="PENDING"),MAX(0,F43-V43),0))) -> 0
A44: =IF(B44="","",ROW()-4) | V44: =IF(TRIM(Y44)="PAID",SUM(G44,J44,M44,P44,S44),IF(AND(H44<>"",LEN(TRIM(H44))>0),G44,0)+IF(AND(K44<>"",LEN(TRIM(K44))>0),J44,0)+IF(AND(N44<>"",LEN(TRIM(N44))>0),M44,0)+IF(AND(Q44<>"",LEN(TRIM(Q44))>0),P44,0)+IF(AND(T44<>"",LEN(TRIM(T44))>0),S44,0)) -> 0 | W44: =IF(OR(F44="",F44=0),"",MAX(0,F44-V44-AC44)) | X44: =IF(OR(F44=0,F44=""),"-",V44/F44) -> - | AC44: =IF(TRIM(Y44)="PAID",0,IF((IF(AND(OR(H44="",LEN(TRIM(H44))=0),ISNUMBER(G44),G44>0),G44,0)+IF(AND(OR(K44="",LEN(TRIM(K44))=0),ISNUMBER(J44),J44>0),J44,0)+IF(AND(OR(N44="",LEN(TRIM(N44))=0),ISNUMBER(M44),M44>0),M44,0)+IF(AND(OR(Q44="",LEN(TRIM(Q44))=0),ISNUMBER(P44),P44>0),P44,0)+IF(AND(OR(T44="",LEN(TRIM(T44))=0),ISNUMBER(S44),S44>0),S44,0))>0,IF(AND(OR(H44="",LEN(TRIM(H44))=0),ISNUMBER(G44),G44>0),G44,0)+IF(AND(OR(K44="",LEN(TRIM(K44))=0),ISNUMBER(J44),J44>0),J44,0)+IF(AND(OR(N44="",LEN(TRIM(N44))=0),ISNUMBER(M44),M44>0),M44,0)+IF(AND(OR(Q44="",LEN(TRIM(Q44))=0),ISNUMBER(P44),P44>0),P44,0)+IF(AND(OR(T44="",LEN(TRIM(T44))=0),ISNUMBER(S44),S44>0),S44,0),IF(OR(TRIM(Y44)="UPCOMING",TRIM(Y44)="PENDING"),MAX(0,F44-V44),0))) -> 0
A45: =IF(B45="","",ROW()-4) | V45: =IF(TRIM(Y45)="PAID",SUM(G45,J45,M45,P45,S45),IF(AND(H45<>"",LEN(TRIM(H45))>0),G45,0)+IF(AND(K45<>"",LEN(TRIM(K45))>0),J45,0)+IF(AND(N45<>"",LEN(TRIM(N45))>0),M45,0)+IF(AND(Q45<>"",LEN(TRIM(Q45))>0),P45,0)+IF(AND(T45<>"",LEN(TRIM(T45))>0),S45,0)) -> 0 | W45: =IF(OR(F45="",F45=0),"",MAX(0,F45-V45-AC45)) | X45: =IF(OR(F45=0,F45=""),"-",V45/F45) -> - | AC45: =IF(TRIM(Y45)="PAID",0,IF((IF(AND(OR(H45="",LEN(TRIM(H45))=0),ISNUMBER(G45),G45>0),G45,0)+IF(AND(OR(K45="",LEN(TRIM(K45))=0),ISNUMBER(J45),J45>0),J45,0)+IF(AND(OR(N45="",LEN(TRIM(N45))=0),ISNUMBER(M45),M45>0),M45,0)+IF(AND(OR(Q45="",LEN(TRIM(Q45))=0),ISNUMBER(P45),P45>0),P45,0)+IF(AND(OR(T45="",LEN(TRIM(T45))=0),ISNUMBER(S45),S45>0),S45,0))>0,IF(AND(OR(H45="",LEN(TRIM(H45))=0),ISNUMBER(G45),G45>0),G45,0)+IF(AND(OR(K45="",LEN(TRIM(K45))=0),ISNUMBER(J45),J45>0),J45,0)+IF(AND(OR(N45="",LEN(TRIM(N45))=0),ISNUMBER(M45),M45>0),M45,0)+IF(AND(OR(Q45="",LEN(TRIM(Q45))=0),ISNUMBER(P45),P45>0),P45,0)+IF(AND(OR(T45="",LEN(TRIM(T45))=0),ISNUMBER(S45),S45>0),S45,0),IF(OR(TRIM(Y45)="UPCOMING",TRIM(Y45)="PENDING"),MAX(0,F45-V45),0))) -> 0
... A102: =IF(B102="","",ROW()-4) | V102: =IF(TRIM(Y102)="PAID",SUM(G102,J102,M102,P102,S102),IF(AND(H102<>"",LEN(TRIM(H102))>0),G102,0)+IF(AND(K102<>"",LEN(TRIM(K102))>0),J102,0)+IF(AND(N102<>"",LEN(TRIM(N102))>0),M102,0)+IF(AND(Q102<>"",LEN(TRIM(Q102))>0),P102,0)+IF(AND(T102<>"",LEN(TRIM(T102))>0),S102,0)) -> 0 | W102: =IF(OR(F102="",F102=0),"",MAX(0,F102-V102-AC102)) | X102: =IF(OR(F102=0,F102=""),"-",V102/F102) -> - | AC102: =IF(TRIM(Y102)="PAID",0,IF((IF(AND(OR(H102="",LEN(TRIM(H102))=0),ISNUMBER(G102),G102>0),G102,0)+IF(AND(OR(K102="",LEN(TRIM(K102))=0),ISNUMBER(J102),J102>0),J102,0)+IF(AND(OR(N102="",LEN(TRIM(N102))=0),ISNUMBER(M102),M102>0),M102,0)+IF(AND(OR(Q102="",LEN(TRIM(Q102))=0),ISNUMBER(P102),P102>0),P102,0)+IF(AND(OR(T102="",LEN(TRIM(T102))=0),ISNUMBER(S102),S102>0),S102,0))>0,IF(AND(OR(H102="",LEN(TRIM(H102))=0),ISNUMBER(G102),G102>0),G102,0)+IF(AND(OR(K102="",LEN(TRIM(K102))=0),ISNUMBER(J102),J102>0),J102,0)+IF(AND(OR(N102="",LEN(TRIM(N102))=0),ISNUMBER(M102),M102>0),M102,0)+IF(AND(OR(Q102="",LEN(TRIM(Q102))=0),ISNUMBER(P102),P102>0),P102,0)+IF(AND(OR(T102="",LEN(TRIM(T102))=0),ISNUMBER(S102),S102>0),S102,0),IF(OR(TRIM(Y102)="UPCOMING",TRIM(Y102)="PENDING"),MAX(0,F102-V102),0))) -> 0
A103: TOTAL | F103: =SUM(F5:F102) -> 7.5247117e+08 | G103: =SUM(G5:G102) -> 254626830 | J103: =SUM(J5:J102) -> 2.3501001e+08 | M103: =SUM(M5:M102) -> 0 | P103: =SUM(P5:P102) -> 0 | S103: =SUM(S5:S102) -> 27938400 | V103: =SUM(V5:V102) -> 5.0819623e+08 | W103: =SUM(W5:W102) -> 2.1282142e+08 | X103: =IF(OR(F105=0,F105=""),"-",V105/F105) -> - | AC103: =SUM(AC5:AC102) -> 31453515

Sheet VBA_Code
A1: VBA CODE — PAYMENT TRACKER — HITECH ESAP
A3: INSTALLATION :
A4: 1. Alt+F11 → Ouvre l'éditeur VBA
A5: 2. Dans VBAProject, double-clic sur 'MD Register' → Coller CODE A
A6: 3. Clic droit VBAProject > Insérer > Module → Coller CODE B
A7: 4. Enregistrer sous .xlsm (Fichier > Enregistrer sous > Classeur Excel avec macros)
A9: ══════════════════════════════════════════════════════════
A10: CODE A — Coller dans la feuille 'MD Register'
A11: ══════════════════════════════════════════════════════════
A13: Private Sub Worksheet_Change(ByVal Target As Range)
A14: ' Déclenché dès qu'une cellule de la colonne B (Service Provider) change
A15: If Not Intersect(Target, Me.Columns("B")) Is Nothing Then
... A347: End Sub

Sheet README
A1: FIELD GUIDE — ESG/ESAP PAYMENT TRACKER
A2: HITECH Construction Company Ltd | Final Version | Do not modify workbook structure
A4: ══════════════════════════════════════════════════════════
A5: 1. GOLDEN RULE — ENTER DATA ONLY IN 'MD Register'
A6: ══════════════════════════════════════════════════════════
A8: Col F — Contract Amount : Enter total contract value. Always.
A9: Col G/J/M/P — Tranches 1-4 : Enter amount when actual payment is made or scheduled.
A10: Col S — ONE-SHOT : For single-payment contracts.
A11: Col Y — Status : PAID / PARTIAL / UPCOMING / PENDING only.
A12: Col V — Total Paid : AUTO-FORMULA. Never edit.
A13: Col W — Balance : AUTO-FORMULA. Never edit.
A14: Col X — % Paid : AUTO-FORMULA. Never edit.
... A61: VBA_Code → Macro to install for full automation.

Sheet Lists
A1: Status | B1: Project | C1: Category | D1: Service Provider | F1: P&C Name | G1: MD Register Name
A2: PAID | B2: LCCH SEC 1 | C2: ESAP SEC 1 | D2: NCF | F2: Nigerian Conservation Foundation (NCF) | G2: NCF
A3: PENDING | B3: LCCH SEC 1&2 | C3: ESAP SEC 1 &2 | D3: DynaSmart | F3: DynaSmart (Ibrahim Salau) | G3: DynaSmart
A4: PARTIAL | B4: LCCH SEC 2 | C4: ESAP SOK | D4: CEO Advisory | F4: EddiePerez Investment Ltd | G4: Eddie Perez Limited
A5: NO INVOICE | B5: LCCH SEC 3 | C5: CNA | D5: Eddie Perez Limited | F5: 3FM Solutions Ltd | G5: 3FM Solutions
A6: UPCOMING | B6: LCCH SEC 4 | C6: CSR | D6: David Omaghomi | F6: Natural Eco-Capital Ltd
A7: Active | B7: LCCH SEC 5 | C7: ESAP Study | D7: Ndoni Logistic | F7: Ndoni Logistics | G7: Ndoni Logistic
A8: Signed - Pending | B8: LCCH SEC 6 | C8: Audit | D8: Hitech-CRM | F8: David Omaghomi | G8: David Omaghomi
A9: Budget Submitted | B9: SBS SOKOTO | C9: Community Activities | D9: Beachtv Media Limited | F9: H
A10: Planned | B10: SBS KEBBI | C10: Project E&S Requirements | D10: G&B PRINTING PRESS AND BUSINESS CENTER
A11: Closed | B11: TRANS SAHARA | C11: LRP | D11: Lifeline Option Enterprises
C12: ESAP-BMP | D12: CRM Office and SRAP Team
C13: ESAP-SRAP | D13: EcoConserv
C14: ESAP-LRP | D14: Hitech CRM
C15: ESAP-SE | D15: Asili
C16: ECM | D16: Other
C17: CRM
C18: CSR-CNA

Sheet Projects & Contracts
A1: ESAP & ESG — PROJECTS & CONTRACTS
A3: # | B3: Service Provider | C3: Type | D3: Scope / Activity | E3: Category | F3: Contract Value (₦) | G3: Project | H3: Section | I3: Status
A4: 1 | B4: Nigerian Conservation Foundation (NCF) | C4: Consultancy | D4: Biodiversity Management Plan (BMP) | E4: ESAP-BMP | F4: =IFERROR(SUMIF('MD Register'!$B$5:$B$20,VLOOKUP(B4,Lists!$F$2:$G$8,2,FALSE()),'MD Register'!$F$5:$F$20),0) -> 82934896 | G4: LCCH SEC 1&2 | H4: LCCH S1 & S2 | I4: =IFERROR(IF(SUMIF('MD Register'!$B$5:$B$70,VLOOKUP(B4,Lists!$F$2:$G$8,2,FALSE()),'MD Register'!$V$5:$V$70)=0,IF(SUMIF('MD Register'!$B$5:$B$70,VLOOKUP(B4,Lists!$F$2:$G$8,2,FALSE()),'MD Register'!$F$5:$F$70)=0,"TBC","PENDING"),IF(SUMIF('MD Register'!$B$5:$B$70,VLOOKUP(B4,Lists!$F$2:$G$8,2,FALSE()),'MD Register'!$W$5:$W$70)<=0,"Closed","Active")),"TBC") -> Active
A5: 2 | B5: DynaSmart (Ibrahim Salau) | C5: Consultancy | D5: Supplementary Resettlement Action Plan (SRAP) | E5: ESAP-SRAP | F5: =IFERROR(SUMIF('MD Register'!$B$5:$B$20,VLOOKUP(B5,Lists!$F$2:$G$8,2,FALSE()),'MD Register'!$F$5:$F$20),0) -> 4.5419667e+08 | G5: LCCH SEC 1 | H5: LCCH Section 1 | I5: =IFERROR(IF(SUMIF('MD Register'!$B$5:$B$70,VLOOKUP(B5,Lists!$F$2:$G$8,2,FALSE()),'MD Register'!$V$5:$V$70)=0,IF(SUMIF('MD Register'!$B$5:$B$70,VLOOKUP(B5,Lists!$F$2:$G$8,2,FALSE()),'MD Register'!$F$5:$F$70)=0,"TBC","PENDING"),IF(SUMIF('MD Register'!$B$5:$B$70,VLOOKUP(B5,Lists!$F$2:$G$8,2,FALSE()),'MD Register'!$W$5:$W$70)<=0,"Closed","Active")),"TBC") -> Active
A6: 3 | B6: EddiePerez Investment Ltd | C6: Consultancy | D6: Socioeconomic Survey + OD Survey + HRRA | E6: ESAP-LRP | F6: =IFERROR(SUMIF('MD Register'!$B$5:$B$20,VLOOKUP(B6,Lists!$F$2:$G$8,2,FALSE()),'MD Register'!$F$5:$F$20),0) -> 0 | G6: LCCH SEC 1&2 | H6: LCCH S1 & S2 | I6: =IFERROR(IF(SUMIF('MD Register'!$B$5:$B$70,VLOOKUP(B6,Lists!$F$2:$G$8,2,FALSE()),'MD Register'!$V$5:$V$70)=0,IF(SUMIF('MD Register'!$B$5:$B$70,VLOOKUP(B6,Lists!$F$2:$G$8,2,FALSE()),'MD Register'!$F$5:$F$70)=0,"TBC","PENDING"),IF(SUMIF('MD Register'!$B$5:$B$70,VLOOKUP(B6,Lists!$F$2:$G$8,2,FALSE()),'MD Register'!$W$5:$W$70)<=0,"Closed","Active")),"TBC") -> TBC
A7: 4 | B7: 3FM Solutions Ltd | C7: Consultancy | D7: Stakeholder Engagement Audit | E7: ESAP-SE | F7: =IFERROR(SUMIF('MD Register'!$B$5:$B$20,VLOOKUP(B7,Lists!$F$2:$G$8,2,FALSE()),'MD Register'!$F$5:$F$20),0) -> 0 | G7: LCCH SEC 1&2 | H7: LCCH S1 & S2 | I7: =IFERROR(IF(SUMIF('MD Register'!$B$5:$B$70,VLOOKUP(B7,Lists!$F$2:$G$8,2,FALSE()),'MD Register'!$V$5:$V$70)=0,IF(SUMIF('MD Register'!$B$5:$B$70,VLOOKUP(B7,Lists!$F$2:$G$8,2,FALSE()),'MD Register'!$F$5:$F$70)=0,"TBC","PENDING"),IF(SUMIF('MD Register'!$B$5:$B$70,VLOOKUP(B7,Lists!$F$2:$G$8,2,FALSE()),'MD Register'!$W$5:$W$70)<=0,"Closed","Active")),"TBC") -> TBC
A8: 5 | B8: Natural Eco-Capital Ltd | C8: Monitoring | D8: Environmental Compliance Monitoring (ECM) | E8: ECM | F8: =IFERROR(SUMIF('MD Register'!$B$5:$B$20,VLOOKUP(B8,Lists!$F$2:$G$8,2,FALSE()),'MD Register'!$F$5:$F$20),0) -> 0 | G8: LCCH SEC 1&2 | H8: LCCH S1 & S2 | I8: =IFERROR(IF(SUMIF('MD Register'!$B$5:$B$70,VLOOKUP(B8,Lists!$F$2:$G$8,2,FALSE()),'MD Register'!$V$5:$V$70)=0,IF(SUMIF('MD Register'!$B$5:$B$70,VLOOKUP(B8,Lists!$F$2:$G$8,2,FALSE()),'MD Register'!$F$5:$F$70)=0,"TBC","PENDING"),IF(SUMIF('MD Register'!$B$5:$B$70,VLOOKUP(B8,Lists!$F$2:$G$8,2,FALSE()),'MD Register'!$W$5:$W$70)<=0,"Closed","Active")),"TBC") -> TBC
A9: 6 | B9: Ndoni Logistics | C9: Services | D9: Community Relations Management (CRM) | E9: CRM | F9: =IFERROR(SUMIF('MD Register'!$B$5:$B$20,VLOOKUP(B9,Lists!$F$2:$G$8,2,FALSE()),'MD Register'!$F$5:$F$20),0) -> 0 | G9: LCCH SEC 1&2 | H9: LCCH | I9: =IFERROR(IF(SUMIF('MD Register'!$B$5:$B$70,VLOOKUP(B9,Lists!$F$2:$G$8,2,FALSE()),'MD Register'!$V$5:$V$70)=0,IF(SUMIF('MD Register'!$B$5:$B$70,VLOOKUP(B9,Lists!$F$2:$G$8,2,FALSE()),'MD Register'!$F$5:$F$70)=0,"TBC","PENDING"),IF(SUMIF('MD Register'!$B$5:$B$70,VLOOKUP(B9,Lists!$F$2:$G$8,2,FALSE()),'MD Register'!$W$5:$W$70)<=0,"Closed","Active")),"TBC") -> Closed
A10: 7 | B10: David Omaghomi | C10: Consultant | D10: Community Relations Management (CRM) | E10: CRM | F10: =IFERROR(SUMIF('MD Register'!$B$5:$B$20,VLOOKUP(B10,Lists!$F$2:$G$8,2,FALSE()),'MD Register'!$F$5:$F$20),0) -> 11750000 | G10: LCCH SEC 1&2 | H10: LCCH | I10: =IFERROR(IF(SUMIF('MD Register'!$B$5:$B$70,VLOOKUP(B10,Lists!$F$2:$G$8,2,FALSE()),'MD Register'!$V$5:$V$70)=0,IF(SUMIF('MD Register'!$B$5:$B$70,VLOOKUP(B10,Lists!$F$2:$G$8,2,FALSE()),'MD Register'!$F$5:$F$70)=0,"TBC","PENDING"),IF(SUMIF('MD Register'!$B$5:$B$70,VLOOKUP(B10,Lists!$F$2:$G$8,2,FALSE()),'MD Register'!$W$5:$W$70)<=0,"Closed","Active")),"TBC") -> Closed
A11: ANTICIPATION — CSR / CNA
A12: 8 | B12: TBD | C12: CSR | D12: Corporate Social Responsibility - CNA | E12: CSR-CNA | G12: LCCH SEC 1 | H12: — | I12: Budget Submitted
A13: 9 | B13: TBD | C13: CSR | D13: Corporate Social Responsibility - CNA | E13: CSR-CNA | G13: LCCH SEC 2 | H13: — | I13: Budget Submitted
A14: 10 | B14: TBD | C14: CSR | D14: Corporate Social Responsibility - CNA | E14: CSR-CNA | G14: LCCH SEC 3 | H14: — | I14: Budget Submitted
A15: 11 | B15: TBD | C15: CSR | D15: Corporate Social Responsibility - CNA | E15: CSR-CNA | G15: LCCH SEC 4 | H15: — | I15: Budget Submitted
A16: 12 | B16: TBD | C16: CSR | D16: Corporate Social Responsibility - CNA | E16: CSR-CNA | G16: LCCH SEC 5 | H16: — | I16: Budget Submitted
A17: 13 | B17: TBD | C17: CSR | D17: Corporate Social Responsibility - CNA | E17: CSR-CNA | G17: SBS SOKOTO | H17: — | I17: Budget Submitted
A18: 14 | B18: TBD | C18: CSR | D18: Corporate Social Responsibility - CNA | E18: CSR-CNA | G18: SBS KEBBI | H18: — | I18: Budget Submitted
A19: 15 | B19: TBD | C19: CSR | D19: Corporate Social Responsibility - CNA | E19: CSR-CNA | G19: TRANS SAHARA | H19: — | I19: Budget Submitted
A20: ANTICIPATION — LRP
A21: 16 | B21: TBD | C21: Consultancy | D21: Livelihood Restoration Program | E21: LRP | G21: LCCH SEC 1 | H21: — | I21: Budget Submitted
A22: 17 | B22: TBD | C22: Consultancy | D22: Livelihood Restoration Program | E22: LRP | G22: LCCH SEC 2 | H22: — | I22: Budget Submitted
A23: 18 | B23: TBD | C23: Consultancy | D23: Livelihood Restoration Program | E23: LRP | G23: LCCH SEC 3 | H23: — | I23: Budget Submitted
A24: 19 | B24: TBD | C24: Consultancy | D24: Livelihood Restoration Program | E24: LRP | G24: LCCH SEC 4 | H24: — | I24: Budget Submitted
A25: 20 | B25: TBD | C25: Consultancy | D25: Livelihood Restoration Program | E25: LRP | G25: LCCH SEC 5 | H25: — | I25: Budget Submitted
A26: 21 | B26: TBD | C26: Consultancy | D26: Livelihood Restoration Program | E26: LRP | G26: SBS SOKOTO | H26: — | I26: Budget Submitted
A27: 22 | B27: TBD | C27: Consultancy | D27: Livelihood Restoration Program | E27: LRP | G27: SBS KEBBI | H27: — | I27: Budget Submitted
A28: 23 | B28: TBD | C28: Consultancy | D28: Livelihood Restoration Program | E28: LRP | G28: TRANS SAHARA | H28: — | I28: Budget Submitted
A29: ANTICIPATION — OTHER ACTIVITIES
A30: 24 | B30: TBD | C30: Various | D30: Other ESG/ESAP Activities | E30: OTHER ACTIVITIES | G30: LCCH SEC 1 | H30: — | I30: Planned
A31: 25 | B31: TBD | C31: Various | D31: Other ESG/ESAP Activities | E31: OTHER ACTIVITIES | G31: LCCH SEC 2 | H31: — | I31: Planned
A32: 26 | B32: TBD | C32: Various | D32: Other ESG/ESAP Activities | E32: OTHER ACTIVITIES | G32: LCCH SEC 3 | H32: — | I32: Planned
A33: 27 | B33: TBD | C33: Various | D33: Other ESG/ESAP Activities | E33: OTHER ACTIVITIES | G33: LCCH SEC 4 | H33: — | I33: Planned
A34: 28 | B34: TBD | C34: Various | D34: Other ESG/ESAP Activities | E34: OTHER ACTIVITIES | G34: LCCH SEC 5 | H34: — | I34: Planned
A35: 29 | B35: TBD | C35: Various | D35: Other ESG/ESAP Activities | E35: SRAP/GRC Activities- April, 4, 2026 | F35: 9228000 | G35: SBS SOKOTO | H35: — | I35: Planned
A36: 30 | B36: EcoConserv | C36: ESAP SEC 1 | D36: Other ESG/ESAP Activities | E36: HURRI - LCCH 40% | F36: 24612600 | G36: SBS KEBBI | H36: — | I36: Planned | J36: 9379015
A37: 31 | G37: TRANS SAHARA | H37: — | I37: Planned
E38: TOTAL | F38: =SUM(F4:F37) -> 5.8272217e+08

Sheet Export_HTML
A1: ⚠️ SOURCE: Auto-calculated from 'MD Register'. DO NOT EDIT. For HTML export only. Updated in real-time via formulas.
A2: HITECH Construction Company Ltd
A3: ESG & ESAP Service Provider Payments Dashboard
A5: Total Committed (₦) | B5: Total Paid (₦) | C5: Pipeline (₦) | D5: Outstanding Balance (₦) | E5: Payment Rate
A6: =SUM('MD Register'!F5:F102) -> 7.5247117e+08 | B6: =SUM('MD Register'!V5:V102) -> 5.0819623e+08 | C6: =SUM('MD Register'!AC5:AC102) -> 31453515 | D6: =A6-B6-C6 -> 2.1282142e+08 | E6: =IF(A6=0,0,B6/A6) -> 0.6753697
A8: # | B8: Service Provider | C8: Category | D8: Project | E8: Description | F8: Contract Amount (₦) | G8: Total Paid (₦) | H8: Pipeline (₦) | I8: Balance (₦) | J8: % Paid | K8: Status
A9: =IF('MD Register'!B5="","",'MD Register'!A5) -> 1 | B9: =IF('MD Register'!B5="","",'MD Register'!B5) -> NCF | C9: =IF('MD Register'!B5="","",'MD Register'!C5) -> ESAP-BMP | D9: =IF('MD Register'!B5="","",'MD Register'!D5) -> LCCH SEC 1&2 | E9: =IF('MD Register'!B5="","",'MD Register'!E5) -> BMP Implementation Phase 1+ 2 | F9: =IF('MD Register'!B5="","",'MD Register'!F5) -> 82934896 | G9: =IF('MD Register'!B5="","",'MD Register'!V5) -> 62264320 | H9: =IF('MD Register'!B5="","",'MD Register'!AC5) -> 0 | I9: =IF('MD Register'!B5="","",'MD Register'!W5) -> 20670576 | J9: =IF('MD Register'!B5="","",'MD Register'!X5) -> 0.75076142 | K9: =IF('MD Register'!B5="","",'MD Register'!Y5) -> PARTIAL
A10: =IF('MD Register'!B6="","",'MD Register'!A6) -> 2 | B10: =IF('MD Register'!B6="","",'MD Register'!B6) -> DynaSmart | C10: =IF('MD Register'!B6="","",'MD Register'!C6) -> ESAP-SRAP | D10: =IF('MD Register'!B6="","",'MD Register'!D6) -> LCCH SEC 1 | E10: =IF('MD Register'!B6="","",'MD Register'!E6) -> SRAP - Contract signing (35%) + Inception Report (30%) | F10: =IF('MD Register'!B6="","",'MD Register'!F6) -> 4.5419667e+08 | G10: =IF('MD Register'!B6="","",'MD Register'!V6) -> 2.950982e+08 | H10: =IF('MD Register'!B6="","",'MD Register'!AC6) -> 0 | I10: =IF('MD Register'!B6="","",'MD Register'!W6) -> 1.5909847e+08 | J10: =IF('MD Register'!B6="","",'MD Register'!X6) -> 0.64971458 | K10: =IF('MD Register'!B6="","",'MD Register'!Y6) -> PARTIAL
A11: =IF('MD Register'!B7="","",'MD Register'!A7) -> 3 | B11: =IF('MD Register'!B7="","",'MD Register'!B7) -> CEO Advisory | C11: =IF('MD Register'!B7="","",'MD Register'!C7) -> HRRA | D11: =IF('MD Register'!B7="","",'MD Register'!D7) -> LCCH SEC 1 | E11: =IF('MD Register'!B7="","",'MD Register'!E7) -> Mobilization (30%) + Draft Report 30% | F11: =IF('MD Register'!B7="","",'MD Register'!F7) -> 10050000 | G11: =IF('MD Register'!B7="","",'MD Register'!V7) -> 6030000 | H11: =IF('MD Register'!B7="","",'MD Register'!AC7) -> 0 | I11: =IF('MD Register'!B7="","",'MD Register'!W7) -> 4020000 | J11: =IF('MD Register'!B7="","",'MD Register'!X7) -> 0.6 | K11: =IF('MD Register'!B7="","",'MD Register'!Y7) -> PARTIAL
A12: =IF('MD Register'!B8="","",'MD Register'!A8) -> 4 | B12: =IF('MD Register'!B8="","",'MD Register'!B8) -> Eddie Perez Limited | C12: =IF('MD Register'!B8="","",'MD Register'!C8) -> OD SURVEY | D12: =IF('MD Register'!B8="","",'MD Register'!D8) -> LCCH SEC 1 | E12: =IF('MD Register'!B8="","",'MD Register'!E8) -> Mobilization fee for survey (60%) + Draft Report (30%) | F12: =IF('MD Register'!B8="","",'MD Register'!F8) -> 53793000 | G12: =IF('MD Register'!B8="","",'MD Register'!V8) -> 48413700 | H12: =IF('MD Register'!B8="","",'MD Register'!AC8) -> 0 | I12: =IF('MD Register'!B8="","",'MD Register'!W8) -> 5379300 | J12: =IF('MD Register'!B8="","",'MD Register'!X8) -> 0.9 | K12: =IF('MD Register'!B8="","",'MD Register'!Y8) -> PARTIAL
A13: =IF('MD Register'!B9="","",'MD Register'!A9) -> 5 | B13: =IF('MD Register'!B9="","",'MD Register'!B9) -> Eddie Perez Limited | C13: =IF('MD Register'!B9="","",'MD Register'!C9) -> SOCIO ECONOMIC SURVEYS | D13: =IF('MD Register'!B9="","",'MD Register'!D9) -> LCCH SEC 1&2 | E13: =IF('MD Register'!B9="","",'MD Register'!E9) -> Mobilization (50%) + Draft report (30%) | F13: =IF('MD Register'!B9="","",'MD Register'!F9) -> 76871100 | G13: =IF('MD Register'!B9="","",'MD Register'!V9) -> 61067832 | H13: =IF('MD Register'!B9="","",'MD Register'!AC9) -> 0 | I13: =IF('MD Register'!B9="","",'MD Register'!W9) -> 15803268 | J13: =IF('MD Register'!B9="","",'MD Register'!X9) -> 0.7944186 | K13: =IF('MD Register'!B9="","",'MD Register'!Y9) -> PARTIAL
A14: =IF('MD Register'!B10="","",'MD Register'!A10) -> 6 | B14: =IF('MD Register'!B10="","",'MD Register'!B10) -> David Omaghomi | C14: =IF('MD Register'!B10="","",'MD Register'!C10) -> CRM | D14: =IF('MD Register'!B10="","",'MD Register'!D10) -> LCCH SEC 1&2 | E14: =IF('MD Register'!B10="","",'MD Register'!E10) -> Communitiy Awareness Campaigns (June - Sept 2025) | F14: =IF('MD Register'!B10="","",'MD Register'!F10) -> 1750000 | G14: =IF('MD Register'!B10="","",'MD Register'!V10) -> 1750000 | H14: =IF('MD Register'!B10="","",'MD Register'!AC10) -> 0 | I14: =IF('MD Register'!B10="","",'MD Register'!W10) -> 0 | J14: =IF('MD Register'!B10="","",'MD Register'!X10) -> 1 | K14: =IF('MD Register'!B10="","",'MD Register'!Y10) -> PAID
A15: =IF('MD Register'!B11="","",'MD Register'!A11) -> 7 | B15: =IF('MD Register'!B11="","",'MD Register'!B11) -> Hitech-CRM | C15: =IF('MD Register'!B11="","",'MD Register'!C11) -> ESAP SEC 1 | D15: =IF('MD Register'!B11="","",'MD Register'!D11) -> LCCH SEC 1 | E15: =IF('MD Register'!B11="","",'MD Register'!E11) -> GRC Activity | F15: =IF('MD Register'!B11="","",'MD Register'!F11) -> 3964400 | G15: =IF('MD Register'!B11="","",'MD Register'!V11) -> 3964400 | H15: =IF('MD Register'!B11="","",'MD Register'!AC11) -> 0 | I15: =IF('MD Register'!B11="","",'MD Register'!W11) -> 0 | J15: =IF('MD Register'!B11="","",'MD Register'!X11) -> 1 | K15: =IF('MD Register'!B11="","",'MD Register'!Y11) -> PAID
A16: =IF('MD Register'!B12="","",'MD Register'!A12) -> 8 | B16: =IF('MD Register'!B12="","",'MD Register'!B12) -> Beachtv Media Limited | C16: =IF('MD Register'!B12="","",'MD Register'!C12) -> CSR | D16: =IF('MD Register'!B12="","",'MD Register'!D12) -> LCCH SEC 1 | E16: =IF('MD Register'!B12="","",'MD Register'!E12) -> Photography Videography - Lagos City Marathon | F16: =IF('MD Register'!B12="","",'MD Register'!F12) -> 120000 | G16: =IF('MD Register'!B12="","",'MD Register'!V12) -> 120000 | H16: =IF('MD Register'!B12="","",'MD Register'!AC12) -> 0 | I16: =IF('MD Register'!B12="","",'MD Register'!W12) -> 0 | J16: =IF('MD Register'!B12="","",'MD Register'!X12) -> 1 | K16: =IF('MD Register'!B12="","",'MD Register'!Y12) -> PAID
A17: =IF('MD Register'!B13="","",'MD Register'!A13) -> 9 | B17: =IF('MD Register'!B13="","",'MD Register'!B13) -> David Omaghomi | C17: =IF('MD Register'!B13="","",'MD Register'!C13) -> CRM | D17: =IF('MD Register'!B13="","",'MD Register'!D13) -> LCCH SEC 1&2 | E17: =IF('MD Register'!B13="","",'MD Register'!E13) -> Payment for Community Relation Manager retainer fee for 5 months (from June 2025 to October 2025) | F17: =IF('MD Register'!B13="","",'MD Register'!F13) -> 10000000 | G17: =IF('MD Register'!B13="","",'MD Register'!V13) -> 10000000 | H17: =IF('MD Register'!B13="","",'MD Register'!AC13) -> 0 | I17: =IF('MD Register'!B13="","",'MD Register'!W13) -> 0 | J17: =IF('MD Register'!B13="","",'MD Register'!X13) -> 1 | K17: =IF('MD Register'!B13="","",'MD Register'!Y13) -> PAID
A18: =IF('MD Register'!B14="","",'MD Register'!A14) -> 10 | B18: =IF('MD Register'!B14="","",'MD Register'!B14) -> G&B PRINTING PRESS AND BUSINESS CENTER | C18: =IF('MD Register'!B14="","",'MD Register'!C14) -> CRM | D18: =IF('MD Register'!B14="","",'MD Register'!D14) -> LCCH SEC 1&2 | E18: =IF('MD Register'!B14="","",'MD Register'!E14) -> Office supplies | F18: =IF('MD Register'!B14="","",'MD Register'!F14) -> 300000 | G18: =IF('MD Register'!B14="","",'MD Register'!V14) -> 0 | H18: =IF('MD Register'!B14="","",'MD Register'!AC14) -> 300000 | I18: =IF('MD Register'!B14="","",'MD Register'!W14) -> 0 | J18: =IF('MD Register'!B14="","",'MD Register'!X14) -> 0 | K18: =IF('MD Register'!B14="","",'MD Register'!Y14) -> PENDING
A19: =IF('MD Register'!B15="","",'MD Register'!A15) -> 11 | B19: =IF('MD Register'!B15="","",'MD Register'!B15) -> G&B PRINTING PRESS AND BUSINESS CENTER | C19: =IF('MD Register'!B15="","",'MD Register'!C15) -> CRM | D19: =IF('MD Register'!B15="","",'MD Register'!D15) -> LCCH SEC 1&2 | E19: =IF('MD Register'!B15="","",'MD Register'!E15) -> Office supplies | F19: =IF('MD Register'!B15="","",'MD Register'!F15) -> 468000 | G19: =IF('MD Register'!B15="","",'MD Register'!V15) -> 0 | H19: =IF('MD Register'!B15="","",'MD Register'!AC15) -> 468000 | I19: =IF('MD Register'!B15="","",'MD Register'!W15) -> 0 | J19: =IF('MD Register'!B15="","",'MD Register'!X15) -> 0 | K19: =IF('MD Register'!B15="","",'MD Register'!Y15) -> PENDING
A20: =IF('MD Register'!B16="","",'MD Register'!A16) -> 12 | B20: =IF('MD Register'!B16="","",'MD Register'!B16) -> G&B PRINTING PRESS AND BUSINESS CENTER | C20: =IF('MD Register'!B16="","",'MD Register'!C16) -> CRM | D20: =IF('MD Register'!B16="","",'MD Register'!D16) -> LCCH SEC 1&2 | E20: =IF('MD Register'!B16="","",'MD Register'!E16) -> Office supplies | F20: =IF('MD Register'!B16="","",'MD Register'!F16) -> 446500 | G20: =IF('MD Register'!B16="","",'MD Register'!V16) -> 0 | H20: =IF('MD Register'!B16="","",'MD Register'!AC16) -> 446500 | I20: =IF('MD Register'!B16="","",'MD Register'!W16) -> 0 | J20: =IF('MD Register'!B16="","",'MD Register'!X16) -> 0 | K20: =IF('MD Register'!B16="","",'MD Register'!Y16) -> PENDING
... A107: =IF('MD Register'!B103="","",'MD Register'!A103) | B107: =IF('MD Register'!B103="","",'MD Register'!B103) | C107: =IF('MD Register'!B103="","",'MD Register'!C103) | D107: =IF('MD Register'!B103="","",'MD Register'!D103) | E107: =IF('MD Register'!B103="","",'MD Register'!E103) | F107: =IF('MD Register'!B103="","",'MD Register'!F103) | G107: =IF('MD Register'!B103="","",'MD Register'!V103) | H107: =IF('MD Register'!B103="","",'MD Register'!AC103) | I107: =IF('MD Register'!B103="","",'MD Register'!W103) | J107: =IF('MD Register'!B103="","",'MD Register'!X103) | K107: =IF('MD Register'!B103="","",'MD Register'!Y103)
A108: =IF('MD Register'!B104="","",'MD Register'!A104) | B108: =IF('MD Register'!B104="","",'MD Register'!B104) | C108: =IF('MD Register'!B104="","",'MD Register'!C104) | D108: =IF('MD Register'!B104="","",'MD Register'!D104) | E108: =IF('MD Register'!B104="","",'MD Register'!E104) | F108: =IF('MD Register'!B104="","",'MD Register'!F102) | G108: =IF('MD Register'!B104="","",'MD Register'!V102) | H108: =IF('MD Register'!B104="","",'MD Register'!AC102) | I108: =IF('MD Register'!B104="","",'MD Register'!W102) | J108: =IF('MD Register'!B104="","",'MD Register'!X104) | K108: =IF('MD Register'!B104="","",'MD Register'!Y104)
A109: TOTAL | F109: =SUM('MD Register'!F5:F102) -> 7.5247117e+08 | G109: =SUM('MD Register'!V5:V102) -> 5.0819623e+08 | H109: =SUM('MD Register'!AC5:AC102) -> 31453515 | I109: =SUM('MD Register'!W5:W102) -> 2.1282142e+08 | J109: =IF(F109=0,0,G109/F109) -> 0.6753697
A111: META: row_count | B111: =COUNTA('MD Register'!B5:B104) -> 29
A112: META: data_range | B112: A9:K108
A113: META: source_sheet | B113: MD Register
